Sobel-Filter/SobelFilter.v
/*
----------------------------------------------------------------
	 
  vertical edge kernel             horizontal edge kernel
	|-1 0 1|			|-1 -2 -1|
	|-2 0 2|			| 0  0  0|
	|-1 0 1|			| 1  2  1|

		   pixel matrix for cc
		       |lu cu ru|
                       |lc cc rc|
                       |lb cb rb|
----------------------------------------------------------------
*/

module SobelFilter(
  input [7:0] lu, cu, ru,
              lc,     rc,
              lb, cb, rb,
  output [7:0] edge_lum
);
  wire [19:0] gx_squared, gy_squared;
  wire [21:0] squared_sum;
  wire [10:0] edge_grad;
  matrix_mul g_x(.m1u(lu), .m2c(lc), .m1b(lb), .p1u(ru), .p2c(rc), .p1b(rb), .squared(gx_squared));
  matrix_mul g_y(.m1u(lu), .m2c(cu), .m1b(ru), .p1u(lb), .p2c(cb), .p1b(rb), .squared(gy_squared));
  assign squared_sum = gx_squared + gy_squared;
  sqrt g(.radicand(squared_sum), .root(edge_grad));
  assign edge_lum = ~ edge_grad[9:2]; //divide by 4 and subtract that by 255 so edges are black on a white bg
  //assign canny = (edge_lum>8'd200) ? 8'd255 : 8'd0; (sharp cut-off without hysterisis)
endmodule

module sqrt(
  input [21:0] radicand,
  output [10:0] root
);
  integer i; //iterator
  reg [21:0] t; //result of sign test
  reg [10:0] q; //temp sqrt ans
  reg [43:0] ax;
  always @(*) begin
    ax = {22'd0,radicand};
    t = 22'd0;
    q = 11'd0;
    for (i = 0; i < 11; i=i+1) begin
      ax = ax << 2;
      t = ax[43:22] - {q, 2'b01};
      q = q << 1;
      if (t[21] == 1'b0) begin //if zero or +ve
        ax[43:22] = t;
        q[0] = 1'b1;
      end
    end
  end
  assign root = q;
endmodule

module matrix_mul(
  input [7:0] m1u, m2c, m1b, p1u, p2c, p1b,
  output [19:0] squared
);
  reg [10:0] sum;
  reg [8:0] m2,p2;
  always @(*) begin
    m2 = m2c;
    p2 = p2c;
    m2 = m2 << 1;
    p2 = p2 << 1;
    sum = p1u + p2 + p1b - m1u - m2 - m1b;
    sum = sum[10] ? -sum : sum;
  end
  assign squared = sum[9:0]*sum[9:0];
endmodule

Sobel-Filter/SobelFilter_tb.v
`include "SobelFilter.v"

module SobelFilter_tb;
  reg [7:0] lu, cu, ru,
            lc,     rc,
            lb, cb, rb;
  wire [7:0] edge_lum;
  SobelFilter uut(.lu(lu), .cu(cu), .ru(ru),
                  .lc(lc),          .rc(rc),
                  .lb(lb), .cb(cb), .rb(rb),
                  .edge_lum(edge_lum));
  initial begin
    $dumpfile("SobelFilter.vcd");
    $dumpvars(0, SobelFilter_tb);
    repeat (1000) begin
      lu = $urandom_range(0, 255);
      lc = $urandom_range(0, 255);
      lb = $urandom_range(0, 255);
      cu = $urandom_range(0, 255);
      cb = $urandom_range(0, 255);
      ru = $urandom_range(0, 255);
      rc = $urandom_range(0, 255);
      rb = $urandom_range(0, 255);
      #100;
    end
  end
endmodule

Sobel-Filter/SobelFilter.vcd
$date
	Fri Mar 15 03:03:31 2024
$end
$version
	ModelSim Version 10.5b
$end
$timescale
	1ps
$end

$scope module SobelFilter_tb $end
$var reg 8 ! lu [7:0] $end
$var reg 8 " cu [7:0] $end
$var reg 8 # ru [7:0] $end
$var reg 8 $ lc [7:0] $end
$var reg 8 % rc [7:0] $end
$var reg 8 & lb [7:0] $end
$var reg 8 ' cb [7:0] $end
$var reg 8 ( rb [7:0] $end
$var wire 1 ) edge_lum [7] $end
$var wire 1 * edge_lum [6] $end
$var wire 1 + edge_lum [5] $end
$var wire 1 , edge_lum [4] $end
$var wire 1 - edge_lum [3] $end
$var wire 1 . edge_lum [2] $end
$var wire 1 / edge_lum [1] $end
$var wire 1 0 edge_lum [0] $end

$scope module uut $end
$var wire 1 1 lu [7] $end
$var wire 1 2 lu [6] $end
$var wire 1 3 lu [5] $end
$var wire 1 4 lu [4] $end
$var wire 1 5 lu [3] $end
$var wire 1 6 lu [2] $end
$var wire 1 7 lu [1] $end
$var wire 1 8 lu [0] $end
$var wire 1 9 cu [7] $end
$var wire 1 : cu [6] $end
$var wire 1 ; cu [5] $end
$var wire 1 < cu [4] $end
$var wire 1 = cu [3] $end
$var wire 1 > cu [2] $end
$var wire 1 ? cu [1] $end
$var wire 1 @ cu [0] $end
$var wire 1 A ru [7] $end
$var wire 1 B ru [6] $end
$var wire 1 C ru [5] $end
$var wire 1 D ru [4] $end
$var wire 1 E ru [3] $end
$var wire 1 F ru [2] $end
$var wire 1 G ru [1] $end
$var wire 1 H ru [0] $end
$var wire 1 I lc [7] $end
$var wire 1 J lc [6] $end
$var wire 1 K lc [5] $end
$var wire 1 L lc [4] $end
$var wire 1 M lc [3] $end
$var wire 1 N lc [2] $end
$var wire 1 O lc [1] $end
$var wire 1 P lc [0] $end
$var wire 1 Q rc [7] $end
$var wire 1 R rc [6] $end
$var wire 1 S rc [5] $end
$var wire 1 T rc [4] $end
$var wire 1 U rc [3] $end
$var wire 1 V rc [2] $end
$var wire 1 W rc [1] $end
$var wire 1 X rc [0] $end
$var wire 1 Y lb [7] $end
$var wire 1 Z lb [6] $end
$var wire 1 [ lb [5] $end
$var wire 1 \ lb [4] $end
$var wire 1 ] lb [3] $end
$var wire 1 ^ lb [2] $end
$var wire 1 _ lb [1] $end
$var wire 1 ` lb [0] $end
$var wire 1 a cb [7] $end
$var wire 1 b cb [6] $end
$var wire 1 c cb [5] $end
$var wire 1 d cb [4] $end
$var wire 1 e cb [3] $end
$var wire 1 f cb [2] $end
$var wire 1 g cb [1] $end
$var wire 1 h cb [0] $end
$var wire 1 i rb [7] $end
$var wire 1 j rb [6] $end
$var wire 1 k rb [5] $end
$var wire 1 l rb [4] $end
$var wire 1 m rb [3] $end
$var wire 1 n rb [2] $end
$var wire 1 o rb [1] $end
$var wire 1 p rb [0] $end
$var wire 1 ) edge_lum [7] $end
$var wire 1 * edge_lum [6] $end
$var wire 1 + edge_lum [5] $end
$var wire 1 , edge_lum [4] $end
$var wire 1 - edge_lum [3] $end
$var wire 1 . edge_lum [2] $end
$var wire 1 / edge_lum [1] $end
$var wire 1 0 edge_lum [0] $end
$var wire 1 q gx_squared [19] $end
$var wire 1 r gx_squared [18] $end
$var wire 1 s gx_squared [17] $end
$var wire 1 t gx_squared [16] $end
$var wire 1 u gx_squared [15] $end
$var wire 1 v gx_squared [14] $end
$var wire 1 w gx_squared [13] $end
$var wire 1 x gx_squared [12] $end
$var wire 1 y gx_squared [11] $end
$var wire 1 z gx_squared [10] $end
$var wire 1 { gx_squared [9] $end
$var wire 1 | gx_squared [8] $end
$var wire 1 } gx_squared [7] $end
$var wire 1 ~ gx_squared [6] $end
$var wire 1 !! gx_squared [5] $end
$var wire 1 "! gx_squared [4] $end
$var wire 1 #! gx_squared [3] $end
$var wire 1 $! gx_squared [2] $end
$var wire 1 %! gx_squared [1] $end
$var wire 1 &! gx_squared [0] $end
$var wire 1 '! gy_squared [19] $end
$var wire 1 (! gy_squared [18] $end
$var wire 1 )! gy_squared [17] $end
$var wire 1 *! gy_squared [16] $end
$var wire 1 +! gy_squared [15] $end
$var wire 1 ,! gy_squared [14] $end
$var wire 1 -! gy_squared [13] $end
$var wire 1 .! gy_squared [12] $end
$var wire 1 /! gy_squared [11] $end
$var wire 1 0! gy_squared [10] $end
$var wire 1 1! gy_squared [9] $end
$var wire 1 2! gy_squared [8] $end
$var wire 1 3! gy_squared [7] $end
$var wire 1 4! gy_squared [6] $end
$var wire 1 5! gy_squared [5] $end
$var wire 1 6! gy_squared [4] $end
$var wire 1 7! gy_squared [3] $end
$var wire 1 8! gy_squared [2] $end
$var wire 1 9! gy_squared [1] $end
$var wire 1 :! gy_squared [0] $end
$var wire 1 ;! squared_sum [21] $end
$var wire 1 <! squared_sum [20] $end
$var wire 1 =! squared_sum [19] $end
$var wire 1 >! squared_sum [18] $end
$var wire 1 ?! squared_sum [17] $end
$var wire 1 @! squared_sum [16] $end
$var wire 1 A! squared_sum [15] $end
$var wire 1 B! squared_sum [14] $end
$var wire 1 C! squared_sum [13] $end
$var wire 1 D! squared_sum [12] $end
$var wire 1 E! squared_sum [11] $end
$var wire 1 F! squared_sum [10] $end
$var wire 1 G! squared_sum [9] $end
$var wire 1 H! squared_sum [8] $end
$var wire 1 I! squared_sum [7] $end
$var wire 1 J! squared_sum [6] $end
$var wire 1 K! squared_sum [5] $end
$var wire 1 L! squared_sum [4] $end
$var wire 1 M! squared_sum [3] $end
$var wire 1 N! squared_sum [2] $end
$var wire 1 O! squared_sum [1] $end
$var wire 1 P! squared_sum [0] $end
$var wire 1 Q! edge_grad [10] $end
$var wire 1 R! edge_grad [9] $end
$var wire 1 S! edge_grad [8] $end
$var wire 1 T! edge_grad [7] $end
$var wire 1 U! edge_grad [6] $end
$var wire 1 V! edge_grad [5] $end
$var wire 1 W! edge_grad [4] $end
$var wire 1 X! edge_grad [3] $end
$var wire 1 Y! edge_grad [2] $end
$var wire 1 Z! edge_grad [1] $end
$var wire 1 [! edge_grad [0] $end

$scope module g_x $end
$var wire 1 1 m1u [7] $end
$var wire 1 2 m1u [6] $end
$var wire 1 3 m1u [5] $end
$var wire 1 4 m1u [4] $end
$var wire 1 5 m1u [3] $end
$var wire 1 6 m1u [2] $end
$var wire 1 7 m1u [1] $end
$var wire 1 8 m1u [0] $end
$var wire 1 I m2c [7] $end
$var wire 1 J m2c [6] $end
$var wire 1 K m2c [5] $end
$var wire 1 L m2c [4] $end
$var wire 1 M m2c [3] $end
$var wire 1 N m2c [2] $end
$var wire 1 O m2c [1] $end
$var wire 1 P m2c [0] $end
$var wire 1 Y m1b [7] $end
$var wire 1 Z m1b [6] $end
$var wire 1 [ m1b [5] $end
$var wire 1 \ m1b [4] $end
$var wire 1 ] m1b [3] $end
$var wire 1 ^ m1b [2] $end
$var wire 1 _ m1b [1] $end
$var wire 1 ` m1b [0] $end
$var wire 1 A p1u [7] $end
$var wire 1 B p1u [6] $end
$var wire 1 C p1u [5] $end
$var wire 1 D p1u [4] $end
$var wire 1 E p1u [3] $end
$var wire 1 F p1u [2] $end
$var wire 1 G p1u [1] $end
$var wire 1 H p1u [0] $end
$var wire 1 Q p2c [7] $end
$var wire 1 R p2c [6] $end
$var wire 1 S p2c [5] $end
$var wire 1 T p2c [4] $end
$var wire 1 U p2c [3] $end
$var wire 1 V p2c [2] $end
$var wire 1 W p2c [1] $end
$var wire 1 X p2c [0] $end
$var wire 1 i p1b [7] $end
$var wire 1 j p1b [6] $end
$var wire 1 k p1b [5] $end
$var wire 1 l p1b [4] $end
$var wire 1 m p1b [3] $end
$var wire 1 n p1b [2] $end
$var wire 1 o p1b [1] $end
$var wire 1 p p1b [0] $end
$var wire 1 q squared [19] $end
$var wire 1 r squared [18] $end
$var wire 1 s squared [17] $end
$var wire 1 t squared [16] $end
$var wire 1 u squared [15] $end
$var wire 1 v squared [14] $end
$var wire 1 w squared [13] $end
$var wire 1 x squared [12] $end
$var wire 1 y squared [11] $end
$var wire 1 z squared [10] $end
$var wire 1 { squared [9] $end
$var wire 1 | squared [8] $end
$var wire 1 } squared [7] $end
$var wire 1 ~ squared [6] $end
$var wire 1 !! squared [5] $end
$var wire 1 "! squared [4] $end
$var wire 1 #! squared [3] $end
$var wire 1 $! squared [2] $end
$var wire 1 %! squared [1] $end
$var wire 1 &! squared [0] $end
$var reg 11 \! sum [10:0] $end
$var reg 9 ]! m2 [8:0] $end
$var reg 9 ^! p2 [8:0] $end
$upscope $end

$scope module g_y $end
$var wire 1 1 m1u [7] $end
$var wire 1 2 m1u [6] $end
$var wire 1 3 m1u [5] $end
$var wire 1 4 m1u [4] $end
$var wire 1 5 m1u [3] $end
$var wire 1 6 m1u [2] $end
$var wire 1 7 m1u [1] $end
$var wire 1 8 m1u [0] $end
$var wire 1 9 m2c [7] $end
$var wire 1 : m2c [6] $end
$var wire 1 ; m2c [5] $end
$var wire 1 < m2c [4] $end
$var wire 1 = m2c [3] $end
$var wire 1 > m2c [2] $end
$var wire 1 ? m2c [1] $end
$var wire 1 @ m2c [0] $end
$var wire 1 A m1b [7] $end
$var wire 1 B m1b [6] $end
$var wire 1 C m1b [5] $end
$var wire 1 D m1b [4] $end
$var wire 1 E m1b [3] $end
$var wire 1 F m1b [2] $end
$var wire 1 G m1b [1] $end
$var wire 1 H m1b [0] $end
$var wire 1 Y p1u [7] $end
$var wire 1 Z p1u [6] $end
$var wire 1 [ p1u [5] $end
$var wire 1 \ p1u [4] $end
$var wire 1 ] p1u [3] $end
$var wire 1 ^ p1u [2] $end
$var wire 1 _ p1u [1] $end
$var wire 1 ` p1u [0] $end
$var wire 1 a p2c [7] $end
$var wire 1 b p2c [6] $end
$var wire 1 c p2c [5] $end
$var wire 1 d p2c [4] $end
$var wire 1 e p2c [3] $end
$var wire 1 f p2c [2] $end
$var wire 1 g p2c [1] $end
$var wire 1 h p2c [0] $end
$var wire 1 i p1b [7] $end
$var wire 1 j p1b [6] $end
$var wire 1 k p1b [5] $end
$var wire 1 l p1b [4] $end
$var wire 1 m p1b [3] $end
$var wire 1 n p1b [2] $end
$var wire 1 o p1b [1] $end
$var wire 1 p p1b [0] $end
$var wire 1 '! squared [19] $end
$var wire 1 (! squared [18] $end
$var wire 1 )! squared [17] $end
$var wire 1 *! squared [16] $end
$var wire 1 +! squared [15] $end
$var wire 1 ,! squared [14] $end
$var wire 1 -! squared [13] $end
$var wire 1 .! squared [12] $end
$var wire 1 /! squared [11] $end
$var wire 1 0! squared [10] $end
$var wire 1 1! squared [9] $end
$var wire 1 2! squared [8] $end
$var wire 1 3! squared [7] $end
$var wire 1 4! squared [6] $end
$var wire 1 5! squared [5] $end
$var wire 1 6! squared [4] $end
$var wire 1 7! squared [3] $end
$var wire 1 8! squared [2] $end
$var wire 1 9! squared [1] $end
$var wire 1 :! squared [0] $end
$var reg 11 _! sum [10:0] $end
$var reg 9 `! m2 [8:0] $end
$var reg 9 a! p2 [8:0] $end
$upscope $end

$scope module g $end
$var wire 1 ;! radicand [21] $end
$var wire 1 <! radicand [20] $end
$var wire 1 =! radicand [19] $end
$var wire 1 >! radicand [18] $end
$var wire 1 ?! radicand [17] $end
$var wire 1 @! radicand [16] $end
$var wire 1 A! radicand [15] $end
$var wire 1 B! radicand [14] $end
$var wire 1 C! radicand [13] $end
$var wire 1 D! radicand [12] $end
$var wire 1 E! radicand [11] $end
$var wire 1 F! radicand [10] $end
$var wire 1 G! radicand [9] $end
$var wire 1 H! radicand [8] $end
$var wire 1 I! radicand [7] $end
$var wire 1 J! radicand [6] $end
$var wire 1 K! radicand [5] $end
$var wire 1 L! radicand [4] $end
$var wire 1 M! radicand [3] $end
$var wire 1 N! radicand [2] $end
$var wire 1 O! radicand [1] $end
$var wire 1 P! radicand [0] $end
$var wire 1 Q! root [10] $end
$var wire 1 R! root [9] $end
$var wire 1 S! root [8] $end
$var wire 1 T! root [7] $end
$var wire 1 U! root [6] $end
$var wire 1 V! root [5] $end
$var wire 1 W! root [4] $end
$var wire 1 X! root [3] $end
$var wire 1 Y! root [2] $end
$var wire 1 Z! root [1] $end
$var wire 1 [! root [0] $end
$var integer 32 b! i $end
$var reg 22 c! t [21:0] $end
$var reg 11 d! q [10:0] $end
$var reg 44 e! ax [43:0] $end
$upscope $end
$upscope $end
$upscope $end
$enddefinitions $end
#0
$dumpvars
b10111000 !
b10110110 "
b1000110 #
b100110 $
b1110010 %
b1100110 &
b11000110 '
b101110 (
b10010 \!
b1001100 ]!
b11100100 ^!
b1001010 _!
b101101100 `!
b110001100 a!
b1111111111111101111111 c!
b1001100 d!
b110000000000000000000000000 e!
b1011 b!
00
0/
1.
1-
0,
1+
1*
1)
0&!
0%!
1$!
0#!
0"!
0!!
1~
0}
1|
0{
0z
0y
0x
0w
0v
0u
0t
0s
0r
0q
0:!
09!
18!
07!
06!
15!
14!
03!
12!
01!
10!
0/!
1.!
0-!
0,!
0+!
0*!
0)!
0(!
0'!
0P!
0O!
0N!
1M!
0L!
1K!
0J!
1I!
0H!
1G!
1F!
0E!
1D!
0C!
0B!
0A!
0@!
0?!
0>!
0=!
0<!
0;!
0[!
0Z!
1Y!
1X!
0W!
0V!
1U!
0T!
0S!
0R!
0Q!
0p
1o
1n
1m
0l
1k
0j
0i
0h
1g
1f
0e
0d
0c
1b
1a
0`
1_
1^
0]
0\
1[
1Z
0Y
0X
1W
0V
0U
1T
1S
1R
0Q
0P
1O
1N
0M
0L
1K
0J
0I
0H
1G
1F
0E
0D
0C
1B
0A
0@
1?
1>
0=
1<
1;
0:
19
08
07
06
15
14
13
02
11
$end
#100
b1100111 !
b111010 $
b1101010 &
b10110100 "
b1101111 '
b1010110 #
b110101 %
b11010100 (
0o
0m
1l
0k
1j
1i
1X
0W
1V
0R
1D
1h
1e
1c
0a
0?
0^
1]
0N
1M
1L
18
17
16
05
04
12
01
b111010 ]!
b110101 ^!
b1110100 ]!
b1101010 ^!
b1001111 \!
b10110100 `!
b1101111 a!
b101101000 `!
b11011110 a!
b11111110111 _!
b1001 _!
1:!
08!
16!
05!
02!
00!
0.!
1&!
0$!
1!!
0|
1y
1x
1O!
0M!
1L!
0G!
0F!
1E!
b1100010110010 e!
b0 c!
b0 d!
b0 b!
b110001011001000 e!
b1111111111111111111111 c!
b1 b!
b11000101100100000 e!
b10 b!
b1100010110010000000 e!
b11 b!
b110001011001000000000 e!
b100 b!
b11000101100100000000000 e!
b0 c!
b1000101100100000000000 e!
b1 d!
b101 b!
b100010110010000000000000 e!
b1111111111111111111101 c!
b10 d!
b110 b!
b10001011001000000000000000 e!
b1111111111111111111111 c!
b100 d!
b111 b!
b1000101100100000000000000000 e!
b10001 c!
b1000 d!
b100011100100000000000000000 e!
b1001 d!
b1000 b!
b10001110010000000000000000000 e!
b100010 c!
b10010 d!
b1000100010000000000000000000 e!
b10011 d!
b1001 b!
b100010001000000000000000000000 e!
b111011 c!
b100110 d!
b1110111000000000000000000000 e!
b100111 d!
b1010 b!
b111011100000000000000000000000 e!
b1010001 c!
b1001110 d!
b10100010000000000000000000000 e!
b1001111 d!
b1011 b!
1[!
1Z!
#200
b10101110 !
b1111101 $
b11011011 &
b101 "
b11100011 '
b100000 #
b11100101 %
b101 (
1p
0l
0j
0i
0T
1R
1Q
0G
0F
0D
1C
0B
0f
0e
1a
1@
0<
0;
09
1`
1\
0[
1Y
1P
0O
1N
1J
08
15
02
11
b1111101 ]!
b11100101 ^!
b11111010 ]!
b111001010 ^!
b11101101100 \!
b10010100 \!
b101 `!
b11100011 a!
b1010 `!
b111000110 a!
b111001110 _!
0:!
18!
06!
13!
12!
1,!
1*!
1)!
0&!
1"!
0!!
0~
1}
1|
1z
0y
1v
0O!
1N!
0K!
1J!
0I!
1H!
1G!
1F!
0E!
1A!
1@!
1?!
b111001011101010100 e!
b0 c!
b0 d!
b0 b!
b11100101110101010000 e!
b1111111111111111111111 c!
b1 b!
b1110010111010101000000 e!
b10 b!
b111001011101010100000000 e!
b10 c!
b101001011101010100000000 e!
b1 d!
b11 b!
b10100101110101010000000000 e!
b101 c!
b10 d!
b1010101110101010000000000 e!
b11 d!
b100 b!
b101010111010101000000000000 e!
b1000 c!
b110 d!
b10000111010101000000000000 e!
b111 d!
b101 b!
b1000011101010100000000000000 e!
b100 c!
b1110 d!
b1001101010100000000000000 e!
b1111 d!
b110 b!
b100110101010000000000000000 e!
b1111111111111111010110 c!
b11110 d!
b111 b!
b10011010101000000000000000000 e!
b1111111111111111010100 c!
b111100 d!
b1000 b!
b1001101010100000000000000000000 e!
b1000100 c!
b1111000 d!
b10001000100000000000000000000 e!
b1111001 d!
b1001 b!
b1000100010000000000000000000000 e!
b1111111111111100101100 c!
b11110010 d!
b1010 b!
b100010001000000000000000000000000 e!
b1111011 c!
b111100100 d!
b11110110000000000000000000000 e!
b111100101 d!
b1011 b!
0Z!
0X!
1V!
1T!
1S!
1/
0-
0+
0*
#300
b100101 !
b11101001 $
b1011101 &
b10001010 "
b1011000 '
b10001011 #
b1010110 %
b11001001 (
0n
1m
1j
1i
0X
1W
1T
0S
0Q
1H
1G
1E
0C
1A
0h
0g
1e
1d
0c
0a
0@
1?
0>
1=
19
0_
1^
0Y
0N
0L
1I
18
07
05
01
b11101001 ]!
b1010110 ^!
b111010010 ]!
b10101100 ^!
b11110101100 \!
b1010100 \!
b10001010 `!
b1011000 a!
b100010100 `!
b10110000 a!
b10010 _!
03!
0,!
0*!
0)!
1{
0z
1y
0v
1I!
0H!
0G!
1E!
0A!
0@!
0?!
b1110011010100 e!
b0 c!
b0 d!
b0 b!
b111001101010000 e!
b1111111111111111111111 c!
b1 b!
b11100110101000000 e!
b10 b!
b1110011010100000000 e!
b11 b!
b111001101010000000000 e!
b100 b!
b11100110101000000000000 e!
b0 c!
b1100110101000000000000 e!
b1 d!
b101 b!
b110011010100000000000000 e!
b1111111111111111111110 c!
b10 d!
b110 b!
b11001101010000000000000000 e!
b11 c!
b100 d!
b111101010000000000000000 e!
b101 d!
b111 b!
b11110101000000000000000000 e!
b1111111111111111111010 c!
b1010 d!
b1000 b!
b1111010100000000000000000000 e!
b10100 c!
b10100 d!
b101000100000000000000000000 e!
b10101 d!
b1001 b!
b10100010000000000000000000000 e!
b1111111111111111111100 c!
b101010 d!
b1010 b!
b1010001000000000000000000000000 e!
b10011011 c!
b1010100 d!
b100110110000000000000000000000 e!
b1010101 d!
b1011 b!
1W!
0V!
0T!
0S!
0.
1-
1+
1*
#400
b10111001 !
b1000000 $
b10000000 &
b1110 "
b11010100 '
b10001110 #
b11000000 %
b10010111 (
1o
1n
0m
1l
0j
0W
0V
0T
1Q
0H
1F
1f
0e
1a
1>
09
0`
0^
0]
0\
0Z
1Y
0P
0M
0K
0I
06
15
14
11
b1000000 ]!
b11000000 ^!
b10000000 ]!
b110000000 ^!
b11101100 \!
b1110 `!
b11010100 a!
b11100 `!
b110101000 a!
b101011100 _!
08!
16!
04!
1/!
1.!
1,!
1+!
1*!
0{
1v
1u
0N!
0L!
1K!
0J!
1G!
0F!
0E!
1C!
1A!
1?!
b101011001010100000 e!
b0 c!
b0 d!
b0 b!
b10101100101010000000 e!
b1111111111111111111111 c!
b1 b!
b1010110010101000000000 e!
b10 b!
b101011001010100000000000 e!
b1 c!
b11011001010100000000000 e!
b1 d!
b11 b!
b1101100101010000000000000 e!
b10 d!
b11100101010000000000000 e!
b11 d!
b100 b!
b1110010101000000000000000 e!
b1111111111111111111010 c!
b110 d!
b101 b!
b111001010100000000000000000 e!
b11 c!
b1100 d!
b111010100000000000000000 e!
b1101 d!
b110 b!
b11101010000000000000000000 e!
b1111111111111111011001 c!
b11010 d!
b111 b!
b1110101000000000000000000000 e!
b1111111111111111010001 c!
b110100 d!
b1000 b!
b111010100000000000000000000000 e!
b11001 c!
b1101000 d!
b110010000000000000000000000 e!
b1101001 d!
b1001 b!
b11001000000000000000000000000 e!
b1111111111111010111111 c!
b11010010 d!
b1010 b!
b1100100000000000000000000000000 e!
b1111111111111001000111 c!
b110100100 d!
b1011 b!
0[!
0W!
1V!
0U!
1T!
1S!
1.
0-
1,
0+
0*
#500
b100101 !
b11000111 $
b1011000 &
b1010001 "
b110010 '
b100011 #
b1010100 %
b10110011 (
0n
1k
1V
1T
0Q
1H
0F
0E
1C
0A
1g
0f
1c
0b
0a
1@
0?
0>
0=
1<
1:
1]
1\
1Z
0Y
1P
1O
1N
1I
16
05
04
01
b11000111 ]!
b1010100 ^!
b110001110 ]!
b10101000 ^!
b11101110011 \!
b10001101 \!
b1010001 `!
b110010 a!
b10100010 `!
b1100100 a!
b10000101 _!
1:!
17!
10!
0/!
0.!
0+!
0*!
1&!
1#!
0"!
1!!
1z
0x
0u
1O!
0K!
1J!
0C!
0?!
b1001001011000010 e!
b0 c!
b0 d!
b0 b!
b100100101100001000 e!
b1111111111111111111111 c!
b1 b!
b10010010110000100000 e!
b10 b!
b1001001011000010000000 e!
b11 b!
b100100101100001000000000 e!
b1 c!
b10100101100001000000000 e!
b1 d!
b100 b!
b1010010110000100000000000 e!
b0 c!
b10 d!
b10110000100000000000 e!
b11 d!
b101 b!
b1011000010000000000000 e!
b1111111111111111110011 c!
b110 d!
b110 b!
b101100001000000000000000 e!
b1111111111111111101001 c!
b1100 d!
b111 b!
b10110000100000000000000000 e!
b1111111111111111011010 c!
b11000 d!
b1000 b!
b1011000010000000000000000000 e!
b1111111111111111001011 c!
b110000 d!
b1001 b!
b101100001000000000000000000000 e!
b1111111111111111101111 c!
b1100000 d!
b1010 b!
b10110000100000000000000000000000 e!
b101000001 c!
b11000000 d!
b1010000010000000000000000000000 e!
b11000001 d!
b1011 b!
1[!
0Y!
0V!
1U!
0S!
10
1-
0,
1*
#600
b1011010 !
b11100110 $
b11110110 &
b1100101 "
b11101010 '
b1111 #
b11101111 %
b1000100 (
0p
0o
1n
0l
0k
1j
0i
1X
1W
1U
0T
1S
1Q
1F
1E
0C
1e
0d
1b
1a
1>
0<
1;
1_
1^
0]
1[
1Y
0P
1K
08
17
06
15
14
03
12
b11100110 ]!
b11101111 ^!
b111001100 ]!
b111011110 ^!
b11100010101 \!
b11101011 \!
b1100101 `!
b11101010 a!
b11001010 `!
b111010100 a!
b111011011 _!
14!
00!
1.!
1-!
1*!
1)!
1"!
1{
0y
1x
1u
1L!
0J!
0I!
1H!
0G!
1E!
0D!
1B!
0A!
1>!
b1000100100100010010 e!
b0 c!
b0 d!
b0 b!
b100010010010001001000 e!
b1111111111111111111111 c!
b1 b!
b10001001001000100100000 e!
b0 c!
b1001001000100100000 e!
b1 d!
b10 b!
b100100100010010000000 e!
b1111111111111111111011 c!
b10 d!
b11 b!
b10010010001001000000000 e!
b1111111111111111111000 c!
b100 d!
b100 b!
b1001001000100100000000000 e!
b1111111111111111110011 c!
b1000 d!
b101 b!
b100100100010010000000000000 e!
b1111111111111111110001 c!
b10000 d!
b110 b!
b10010010001001000000000000000 e!
b1000 c!
b100000 d!
b10000001001000000000000000 e!
b100001 d!
b111 b!
b1000000100100000000000000000 e!
b1111111111111110011011 c!
b1000010 d!
b1000 b!
b100000010010000000000000000000 e!
b1111111111111101111000 c!
b10000100 d!
b1001 b!
b10000001001000000000000000000000 e!
b1111111111111111110011 c!
b100001000 d!
b1010 b!
b1000000100100000000000000000000000 e!
b1111110001 c!
b1000010000 d!
b11111100010000000000000000000000 e!
b1000010001 d!
b1011 b!
1W!
0U!
0T!
1R!
0.
1,
1+
0)
#700
b11001001 !
b11001011 $
b1000111 &
b11000111 "
b11110010 '
b11100001 #
b10000101 %
b110000 (
0n
1l
1k
0j
0W
0U
0S
0R
0G
0F
0E
1C
1B
1A
0e
1d
1?
0;
19
1`
0\
0[
0Y
1P
0N
1M
0K
18
07
04
11
b11001011 ]!
b10000101 ^!
b110010110 ]!
b100001010 ^!
b11101110101 \!
b10001011 \!
b11000111 `!
b11110010 a!
b110001110 `!
b111100100 a!
b11100100011 _!
b11011101 _!
06!
13!
02!
11!
10!
1/!
0,!
1+!
0*!
0)!
1~
0}
0z
1y
0x
0u
0L!
1J!
0H!
1G!
0B!
1@!
0>!
b10000101001000010 e!
b0 c!
b0 d!
b0 b!
b1000010100100001000 e!
b1111111111111111111111 c!
b1 b!
b100001010010000100000 e!
b10 b!
b10000101001000010000000 e!
b0 c!
b101001000010000000 e!
b1 d!
b11 b!
b10100100001000000000 e!
b1111111111111111111011 c!
b10 d!
b100 b!
b1010010000100000000000 e!
b1111111111111111110111 c!
b100 d!
b101 b!
b101001000010000000000000 e!
b1111111111111111110001 c!
b1000 d!
b110 b!
b10100100001000000000000000 e!
b1111111111111111101001 c!
b10000 d!
b111 b!
b1010010000100000000000000000 e!
b1111111111111111101000 c!
b100000 d!
b1000 b!
b101001000010000000000000000000 e!
b100011 c!
b1000000 d!
b1000110010000000000000000000 e!
b1000001 d!
b1001 b!
b100011001000000000000000000000 e!
b1111111111111110000111 c!
b10000010 d!
b1010 b!
b10001100100000000000000000000000 e!
b101001 c!
b100000100 d!
b1010010000000000000000000000 e!
b100000101 d!
b1011 b!
1Y!
0W!
1S!
0R!
00
1.
0*
1)
#800
b1110110 !
b11101 $
b11010010 &
b10110 "
b11011011 '
b1000000 #
b10110101 %
b10010001 (
1p
0k
1i
1T
1S
0H
0C
0A
1h
1e
0c
0@
1<
0:
09
0`
0^
1\
1Y
0O
1N
1L
0J
0I
08
17
16
05
14
13
01
b11101 ]!
b10110101 ^!
b111010 ]!
b101101010 ^!
b10111001 \!
b10110 `!
b11011011 a!
b101100 `!
b110110110 a!
b1000110111 _!
07!
16!
12!
0/!
0.!
1,!
1(!
0#!
0~
1}
0{
1z
0y
0v
1u
0J!
1I!
1H!
0G!
1F!
1C!
1B!
1>!
b1010110110110000010 e!
b0 c!
b0 d!
b0 b!
b101011011011000001000 e!
b1111111111111111111111 c!
b1 b!
b10101101101100000100000 e!
b0 c!
b101101101100000100000 e!
b1 d!
b10 b!
b10110110110000010000000 e!
b1111111111111111111100 c!
b10 d!
b11 b!
b1011011011000001000000000 e!
b100 d!
b100 b!
b101101101100000100000000000 e!
b101 c!
b1000 d!
b1011101100000100000000000 e!
b1001 d!
b101 b!
b101110110000010000000000000 e!
b1111111111111111110010 c!
b10010 d!
b110 b!
b10111011000001000000000000000 e!
b10100 c!
b100100 d!
b101001000001000000000000000 e!
b100101 d!
b111 b!
b10100100000100000000000000000 e!
b1111111111111110111101 c!
b1001010 d!
b1000 b!
b1010010000010000000000000000000 e!
b11111 c!
b10010100 d!
b111110010000000000000000000 e!
b10010101 d!
b1001 b!
b11111001000000000000000000000 e!
b1111111111111000100111 c!
b100101010 d!
b1010 b!
b1111100100000000000000000000000 e!
b1111111111110101001001 c!
b1001010100 d!
b1011 b!
0[!
1W!
1U!
0S!
1R!
0.
0,
1*
0)
