RGB-Y Fixed Point Modules/rgb2grey_shifting/rgb2grey_shifting.v
module rgb2grey_shifting(
  input [23:0] rgb_pixel,
  output [7:0] grey_pixel
);
  reg [7:0] current, summer;
  always @(*) begin
    summer = 8*{1'b0};    

    //red
    current = rgb_pixel[23:16];
    current = current >> 2;
    summer = current;
    current = current >> 3;
    summer = summer + current;
    current = current >> 1;
    summer = summer + current;

    //green
    current = rgb_pixel[15:8];
    current = current >> 1;
    summer = summer + current;
    current = current >> 3;
    summer = summer + current;
    current = current >> 2;
    summer = summer + current;
    current = current >> 1;
    summer = summer + current;  

    //blue
    current = rgb_pixel[7:0];
    current = current >> 4;
    summer = summer + current;
    current = current >> 1;
    summer = summer + current;
    current = current >> 1;
    summer = summer + current;
    current = current >> 2;
    summer = summer + current;

    summer = summer + 3'b101;
    //compensating for the approximation made by ignoring 2^-8 onwards lower order bits
  end
  assign grey_pixel = summer;
endmodule

/*
//base orginal module
module rgb2grey_shifting(
  input [23:0] rgb_pixel,
  output reg [7:0] grey_pixel
);
  reg [7:0] red, green, blue;
  reg [7:0] red_w, green_w, blue_w;
  always @(*) begin
    red = rgb_pixel[23:16];
    blue = rgb_pixel[15:8];
    green = rgb_pixel[7:0];
    
    red = red >> 2;
    red_w = red;
    red = red >> 3;
    red_w = red_w + red;
    red_w = red >> 1;
    red_w = red_w + red;

    blue = blue >> 1;
    blue_w = blue;
    blue = blue >> 3;
    blue_w = blue_w + blue;
    blue = blue >> 2;
    blue_w = blue_w + blue;
    blue = blue >> 1;
    blue_w = blue_w + blue;  

    green = green >> 4;
    green_w = green;
    green = green >> 1;
    green_w = green_w + green;
    green = green >> 1;
    green_w = green_w + green;
    green = green >> 2;
    green_w = green_w + green;

    grey_pixel = red_w + green_w + blue_w;
  end
endmodule
*/

RGB-Y Fixed Point Modules/rgb2grey_tb/rgb2grey_tb.v
`include "rgb2grey_shifting.v"

module rgb2grey_tb;
  reg [23:0] rgb_pixel;
  wire [7:0] grey_pixel;
  rgb2grey_shifting uut(.rgb_pixel(rgb_pixel), .grey_pixel(grey_pixel));
  initial begin
    $dumpfile("rgb2grey_shifting.vcd");
    $dumpvars(0, rgb2grey_tb);
    repeat (1000) begin
      rgb_pixel = $urandom_range(0,16777215); //2^24-1
      #100;
    end
  end
endmodule

RGB-Y Fixed Point Modules/rgb2grey_shifting/rgb2grey_shifting.vcd
$date
	Sat Mar 02 22:53:06 2024
$end
$version
	ModelSim Version 10.5b
$end
$timescale
	1ps
$end

$scope module rgb2grey_tb $end
$var reg 24 ! rgb_pixel [23:0] $end
$var wire 1 " grey_pixel [7] $end
$var wire 1 # grey_pixel [6] $end
$var wire 1 $ grey_pixel [5] $end
$var wire 1 % grey_pixel [4] $end
$var wire 1 & grey_pixel [3] $end
$var wire 1 ' grey_pixel [2] $end
$var wire 1 ( grey_pixel [1] $end
$var wire 1 ) grey_pixel [0] $end

$scope module uut $end
$var wire 1 * rgb_pixel [23] $end
$var wire 1 + rgb_pixel [22] $end
$var wire 1 , rgb_pixel [21] $end
$var wire 1 - rgb_pixel [20] $end
$var wire 1 . rgb_pixel [19] $end
$var wire 1 / rgb_pixel [18] $end
$var wire 1 0 rgb_pixel [17] $end
$var wire 1 1 rgb_pixel [16] $end
$var wire 1 2 rgb_pixel [15] $end
$var wire 1 3 rgb_pixel [14] $end
$var wire 1 4 rgb_pixel [13] $end
$var wire 1 5 rgb_pixel [12] $end
$var wire 1 6 rgb_pixel [11] $end
$var wire 1 7 rgb_pixel [10] $end
$var wire 1 8 rgb_pixel [9] $end
$var wire 1 9 rgb_pixel [8] $end
$var wire 1 : rgb_pixel [7] $end
$var wire 1 ; rgb_pixel [6] $end
$var wire 1 < rgb_pixel [5] $end
$var wire 1 = rgb_pixel [4] $end
$var wire 1 > rgb_pixel [3] $end
$var wire 1 ? rgb_pixel [2] $end
$var wire 1 @ rgb_pixel [1] $end
$var wire 1 A rgb_pixel [0] $end
$var wire 1 " grey_pixel [7] $end
$var wire 1 # grey_pixel [6] $end
$var wire 1 $ grey_pixel [5] $end
$var wire 1 % grey_pixel [4] $end
$var wire 1 & grey_pixel [3] $end
$var wire 1 ' grey_pixel [2] $end
$var wire 1 ( grey_pixel [1] $end
$var wire 1 ) grey_pixel [0] $end
$var reg 8 B current [7:0] $end
$var reg 8 C summer [7:0] $end
$upscope $end
$upscope $end
$enddefinitions $end
#0
$dumpvars
b10110101010001110111000 !
b0 B
b10001110 C
0)
1(
1'
1&
0%
0$
0#
1"
0A
0@
0?
1>
1=
1<
0;
1:
19
18
07
06
05
14
03
12
01
10
0/
1.
1-
0,
1+
0*
$end
#100
b11101010000110000100110 !
1@
1?
0>
0=
0:
09
08
17
16
04
02
11
00
1/
0.
1,
b0 C
b1110101 B
b11101 B
b11101 C
b11 B
b100000 C
b1 B
b100001 C
b1100 B
b110 B
b100111 C
b0 B
b100110 B
b10 B
b101001 C
b1 B
b101010 C
b0 B
b101111 C
1)
1$
0"
#200
b11011011100101100110 !
1;
19
07
15
14
12
1.
0-
0,
0+
b0 C
b1101 B
b11 B
b11 C
b0 B
b10111001 B
b1011100 B
b1011111 C
b1011 B
b1101010 C
b10 B
b1101100 C
b1 B
b1101101 C
b1100110 B
b110 B
b1110011 C
b11 B
b1110110 C
b1 B
b1110111 C
b0 B
b1111100 C
0)
0(
1%
1#
#300
b101110011110001110110110 !
1=
0;
1:
18
06
05
13
0/
1-
1,
1*
b0 C
b10111001 B
b101110 B
b101110 C
b101 B
b110011 C
b10 B
b110101 C
b11100011 B
b1110001 B
b10100110 C
b1110 B
b10110100 C
b11 B
b10110111 C
b1 B
b10111000 C
b10110110 B
b1011 B
b11000011 C
b101 B
b11001000 C
b10 B
b11001010 C
b0 B
b11001111 C
1)
1(
0%
0$
1"
#400
b11100000100011000110 !
0=
0<
1;
09
08
16
04
03
02
01
10
1/
0-
0,
0*
b0 C
b1110 B
b11 B
b11 C
b0 B
b1000 B
b100 B
b111 C
b0 B
b11000110 B
b1100 B
b10011 C
b110 B
b11001 C
b11 B
b11100 C
b0 B
b100001 C
0(
0'
0&
1$
0#
0"
#500
b100101010110111001000110 !
0:
18
17
14
13
11
00
0.
1-
1*
b0 C
b10010101 B
b100101 B
b100101 C
b100 B
b101001 C
b10 B
b101011 C
b1101110 B
b110111 B
b1100010 C
b110 B
b1101000 C
b1 B
b1101001 C
b0 B
b1000110 B
b100 B
b1101101 C
b10 B
b1101111 C
b1 B
b1110000 C
b0 B
b1110101 C
1'
1%
1#
#600
b110100010000111101110010 !
0?
1=
1<
19
04
03
0/
1+
b0 C
b11010001 B
b110100 B
b110100 C
b110 B
b111010 C
b11 B
b111101 C
b1111 B
b111 B
b1000100 C
b0 B
b1110010 B
b111 B
b1001011 C
b11 B
b1001110 C
b1 B
b1001111 C
b0 B
b1010100 C
0)
0$
#700
b100110111111001100101110 !
1?
1>
0=
0;
07
06
15
14
13
12
10
1.
0+
b0 C
b10011011 B
b100110 B
b100110 C
b100 B
b101010 C
b10 B
b101100 C
b11110011 B
b1111001 B
b10100101 C
b1111 B
b10110100 C
b11 B
b10110111 C
b1 B
b10111000 C
b101110 B
b10 B
b10111010 C
b1 B
b10111011 C
b0 B
b11000000 C
0'
0%
1"
#800
b1101110100010001100111 !
1A
0>
1;
09
08
17
05
04
02
1/
0.
1,
0*
b0 C
b110111 B
b1101 B
b1101 C
b1 B
b1110 C
b0 B
b1000100 B
b100010 B
b110000 C
b100 B
b110100 C
b1 B
b110101 C
b0 B
b1100111 B
b110 B
b111011 C
b11 B
b111110 C
b1 B
b111111 C
b0 B
b1000100 C
1'
0"
#900
b100001100101010100111010 !
0A
0?
1>
1=
0;
19
15
01
0-
0,
1*
b0 C
b10000110 B
b100001 B
b100001 C
b100 B
b100101 C
b10 B
b100111 C
b1010101 B
b101010 B
b1010001 C
b101 B
b1010110 C
b1 B
b1010111 C
b0 B
b111010 B
b11 B
b1011010 C
b1 B
b1011011 C
b0 B
b1100000 C
0'
1$
#1000
b111110010001110001101010 !
0=
1;
09
16
03
11
00
0/
1.
1-
1,
1+
b0 C
b11111001 B
b111110 B
b111110 C
b111 B
b1000101 C
b11 B
b1001000 C
b11100 B
b1110 B
b1010110 C
b1 B
b1010111 C
b0 B
b1101010 B
b110 B
b1011101 C
b11 B
b1100000 C
b1 B
b1100001 C
b0 B
b1100110 C
1(
1'
#1100
b1001011101000110110100 !
0@
1?
0>
1=
0;
1:
19
07
06
13
12
1/
0.
0-
0+
0*
b0 C
b100101 B
b1001 B
b1001 C
b1 B
b1010 C
b0 B
b11010001 B
b1101000 B
b1110010 C
b1101 B
b1111111 C
b11 B
b10000010 C
b1 B
b10000011 C
b10110100 B
b1011 B
b10001110 C
b101 B
b10010011 C
b10 B
b10010101 C
b0 B
b10011010 C
0'
1&
1%
0$
0#
1"
#1200
b101101111101001101111 !
1A
1@
1>
0=
1;
0:
09
18
16
14
01
10
1-
0,
b0 C
b10110 B
b101 B
b101 C
b0 B
b11111010 B
b1111101 B
b10000010 C
b1111 B
b10010001 C
b11 B
b10010100 C
b1 B
b10010101 C
b1101111 B
b110 B
b10011011 C
b11 B
b10011110 C
b1 B
b10011111 C
b0 B
b10100100 C
0(
1'
0&
0%
1$
#1300
b100110110001101001010110 !
0A
0>
1=
0<
04
03
02
11
0/
1.
1*
b0 C
b10011011 B
b100110 B
b100110 C
b100 B
b101010 C
b10 B
b101100 C
b11010 B
b1101 B
b111001 C
b1 B
b111010 C
b0 B
b1010110 B
b101 B
b111111 C
b10 B
b1000001 C
b1 B
b1000010 C
b0 B
b1000111 C
1)
1(
0$
1#
0"
#1400
b110010011011000110101 !
1A
0@
1<
0;
17
06
14
00
0*
b0 C
b11001 B
b110 B
b110 C
b0 B
b110110 B
b11011 B
b100001 C
b11 B
b100100 C
b0 B
b110101 B
b11 B
b100111 C
b1 B
b101000 C
b0 B
b101101 C
0(
1&
1$
0#
#1500
b111011010111011111010100 !
0A
0<
1;
1:
19
13
1/
0-
1,
1+
1*
b0 C
b11101101 B
b111011 B
b111011 C
b111 B
b1000010 C
b11 B
b1000101 C
b1110111 B
b111011 B
b10000000 C
b111 B
b10000111 C
b1 B
b10001000 C
b0 B
b11010100 B
b1101 B
b10010101 C
b110 B
b10011011 C
b11 B
b10011110 C
b0 B
b10100011 C
1(
0'
0&
1"
#1600
b100111110100000010101110 !
1@
1>
0=
1<
0;
09
08
07
05
04
10
1-
0,
0+
b0 C
b10011111 B
b100111 B
b100111 C
b100 B
b101011 C
b10 B
b101101 C
b1000000 B
b100000 B
b1001101 C
b100 B
b1010001 C
b1 B
b1010010 C
b0 B
b10101110 B
b1010 B
b1011100 C
b101 B
b1100001 C
b10 B
b1100011 C
b0 B
b1101000 C
0)
0(
1&
1#
0"
#1700
b111100011000000101111101 !
1A
0@
1=
1;
0:
19
03
12
00
0/
0.
1,
1+
b0 C
b11110001 B
b111100 B
b111100 C
b111 B
b1000011 C
b11 B
b1000110 C
b10000001 B
b1000000 B
b10000110 C
b1000 B
b10001110 C
b10 B
b10010000 C
b1 B
b10010001 C
b1111101 B
b111 B
b10011000 C
b11 B
b10011011 C
b1 B
b10011100 C
b0 B
b10100001 C
1)
0&
0#
1"
#1800
b110011001011011111011011 !
1@
0?
0<
1:
18
17
15
14
01
1/
1.
0-
0,
b0 C
b11001100 B
b110011 B
b110011 C
b110 B
b111001 C
b11 B
b111100 C
b10110111 B
b1011011 B
b10010111 C
b1011 B
b10100010 C
b10 B
b10100100 C
b1 B
b10100101 C
b11011011 B
b1101 B
b10110010 C
b110 B
b10111000 C
b11 B
b10111011 C
b0 B
b11000000 C
0)
0$
1#
#1900
b111011110000111000000101 !
0@
1?
0>
0=
0;
0:
09
16
05
04
02
11
10
1,
b0 C
b11101111 B
b111011 B
b111011 C
b111 B
b1000010 C
b11 B
b1000101 C
b1110 B
b111 B
b1001100 C
b0 B
b101 B
b0 B
b1010001 C
1)
1%
0"
#2000
b110011011000011011100011 !
1@
0?
1<
1;
1:
06
12
00
0,
b0 C
b11001101 B
b110011 B
b110011 C
b110 B
b111001 C
b11 B
b111100 C
b10000110 B
b1000011 B
b1111111 C
b1000 B
b10000111 C
b10 B
b10001001 C
b1 B
b10001010 C
b11100011 B
b1110 B
b10011000 C
b111 B
b10011111 C
b11 B
b10100010 C
b0 B
b10100111 C
1(
1'
0%
1$
0#
1"
#2100
b1000001100100000 !
0A
0@
0;
0:
19
07
01
0/
0.
0+
0*
b0 C
b10000011 B
b1000001 B
b1000001 C
b1000 B
b1001001 C
b10 B
b1001011 C
b1 B
b1001100 C
b100000 B
b10 B
b1001110 C
b1 B
b1001111 C
b0 B
b1010100 C
0)
0(
1%
0$
1#
0"
#2200
b110110100110010111100101 !
1A
1?
1;
1:
08
17
14
13
02
10
1.
1-
1+
1*
b0 C
b11011010 B
b110110 B
b110110 C
b110 B
b111100 C
b11 B
b111111 C
b1100101 B
b110010 B
b1110001 C
b110 B
b1110111 C
b1 B
b1111000 C
b0 B
b11100101 B
b1110 B
b10000110 C
b111 B
b10001101 C
b11 B
b10010000 C
b0 B
b10010101 C
1)
0#
1"
#2300
b111110100111011100000101 !
0<
0;
0:
18
15
1,
b0 C
b11111010 B
b111110 B
b111110 C
b111 B
b1000101 C
b11 B
b1001000 C
b1110111 B
b111011 B
b10000011 C
b111 B
b10001010 C
b1 B
b10001011 C
b0 B
b101 B
b0 B
b10010000 C
0)
0'
#2400
b1101111000110100100101 !
1<
08
16
05
04
03
12
11
1/
0.
0+
0*
b0 C
b110111 B
b1101 B
b1101 C
b1 B
b1110 C
b0 B
b10001101 B
b1000110 B
b1010100 C
b1000 B
b1011100 C
b10 B
b1011110 C
b1 B
b1011111 C
b100101 B
b10 B
b1100001 C
b1 B
b1100010 C
b0 B
b1100111 C
1)
1(
1'
0%
1$
1#
0"
#2500
b110001110001111011101001 !
0?
1>
1;
1:
09
18
15
02
0-
0,
1+
1*
b0 C
b11000111 B
b110001 B
b110001 C
b110 B
b110111 C
b11 B
b111010 C
b11110 B
b1111 B
b1001001 C
b1 B
b1001010 C
b0 B
b11101001 B
b1110 B
b1011000 C
b111 B
b1011111 C
b11 B
b1100010 C
b0 B
b1100111 C
#2600
b100000010010001011101 !
1?
1=
0<
0:
08
06
05
14
01
00
0/
1-
0+
0*
b0 C
b10000 B
b100 B
b100 C
b0 B
b100100 B
b10010 B
b10110 C
b10 B
b11000 C
b0 B
b1011101 B
b101 B
b11101 C
b10 B
b11111 C
b1 B
b100000 C
b0 B
b100101 C
0(
0#
#2700
b1100101001110110001010 !
0A
1@
0?
0=
0;
1:
19
16
15
04
12
10
1,
b0 C
b110010 B
b1100 B
b1100 C
b1 B
b1101 C
b0 B
b10011101 B
b1001110 B
b1011011 C
b1001 B
b1100100 C
b10 B
b1100110 C
b1 B
b1100111 C
b10001010 B
b1000 B
b1101111 C
b100 B
b1110011 C
b10 B
b1110101 C
b0 B
b1111010 C
0)
1(
0'
1&
1%
1#
#2800
b11100010010000101011000 !
0@
1=
1;
0:
07
06
05
14
02
11
00
1+
b0 C
b1110001 B
b11100 B
b11100 C
b11 B
b11111 C
b1 B
b100000 C
b100001 B
b10000 B
b110000 C
b10 B
b110010 C
b0 B
b1011000 B
b101 B
b110111 C
b10 B
b111001 C
b1 B
b111010 C
b0 B
b111111 C
1)
1'
0#
#2900
b100100100110001011 !
1A
1@
0=
0;
1:
16
04
13
01
10
0-
0,
0+
b0 C
b10 B
b0 B
b1001001 B
b100100 B
b100100 C
b100 B
b101000 C
b1 B
b101001 C
b0 B
b10001011 B
b1000 B
b110001 C
b100 B
b110101 C
b10 B
b110111 C
b0 B
b111100 C
0)
0(
#3000
b1111111101000101010110 !
0A
1?
0>
1=
1;
0:
06
15
12
11
1/
1.
1-
1,
b0 C
b111111 B
b1111 B
b1111 C
b1 B
b10000 C
b0 B
b11010001 B
b1101000 B
b1111000 C
b1101 B
b10000101 C
b11 B
b10001000 C
b1 B
b10001001 C
b1010110 B
b101 B
b10001110 C
b10 B
b10010000 C
b1 B
b10010001 C
b0 B
b10010110 C
1(
0&
0$
1"
#3100
b111000111001001111001001 !
1A
0@
0?
1>
0=
1:
18
03
0/
0.
0-
1+
1*
b0 C
b11100011 B
b111000 B
b111000 C
b111 B
b111111 C
b11 B
b1000010 C
b10010011 B
b1001001 B
b10001011 C
b1001 B
b10010100 C
b10 B
b10010110 C
b1 B
b10010111 C
b11001001 B
b1100 B
b10100011 C
b110 B
b10101001 C
b11 B
b10101100 C
b0 B
b10110001 C
1)
0(
0'
1$
#3200
b11011000111001010111001 !
1=
1<
0;
09
14
13
02
01
00
1/
1.
0*
b0 C
b1101100 B
b11011 B
b11011 C
b11 B
b11110 C
b1 B
b11111 C
b1110010 B
b111001 B
b1011000 C
b111 B
b1011111 C
b1 B
b1100000 C
b0 B
b10111001 B
b1011 B
b1101011 C
b101 B
b1110000 C
b10 B
b1110010 C
b0 B
b1110111 C
1(
1'
1#
0"
#3300
b101011011000101000000 !
0A
0>
0=
0<
1;
0:
19
08
03
12
11
0.
1-
0,
0+
b0 C
b10101 B
b101 B
b101 C
b0 B
b10110001 B
b1011000 B
b1011101 C
b1011 B
b1101000 C
b10 B
b1101010 C
b1 B
b1101011 C
b1000000 B
b100 B
b1101111 C
b10 B
b1110001 C
b1 B
b1110010 C
b0 B
b1110111 C
#3400
b100110111101011110000000 !
0;
1:
18
17
04
13
10
0/
1.
1*
b0 C
b10011011 B
b100110 B
b100110 C
b100 B
b101010 C
b10 B
b101100 C
b11010111 B
b1101011 B
b10010111 C
b1101 B
b10100100 C
b11 B
b10100111 C
b1 B
b10101000 C
b10000000 B
b1000 B
b10110000 C
b100 B
b10110100 C
b10 B
b10110110 C
b0 B
b10111011 C
0'
1&
0#
1"
#3500
b111010001011111000001110 !
1@
1?
1>
0:
09
16
14
03
01
00
0-
1,
1+
b0 C
b11101000 B
b111010 B
b111010 C
b111 B
b1000001 C
b11 B
b1000100 C
b10111110 B
b1011111 B
b10100011 C
b1011 B
b10101110 C
b10 B
b10110000 C
b1 B
b10110001 C
b1110 B
b0 B
b10110110 C
0)
1'
0&
#3600
b1001111100100011010100 !
0@
0>
1=
1;
1:
08
07
05
04
13
11
10
1/
0.
0+
0*
b0 C
b100111 B
b1001 B
b1001 C
b1 B
b1010 C
b0 B
b11001000 B
b1100100 B
b1101110 C
b1100 B
b1111010 C
b11 B
b1111101 C
b1 B
b1111110 C
b11010100 B
b1101 B
b10001011 C
b110 B
b10010001 C
b11 B
b10010100 C
b0 B
b10011001 C
1)
0(
0'
1&
0$
#3700
b11111001110100110001110 !
1@
1>
0=
0;
19
14
01
00
1.
1-
1+
b0 C
b1111100 B
b11111 B
b11111 C
b11 B
b100010 C
b1 B
b100011 C
b11101001 B
b1110100 B
b10010111 C
b1110 B
b10100101 C
b11 B
b10101000 C
b1 B
b10101001 C
b10001110 B
b1000 B
b10110001 C
b100 B
b10110101 C
b10 B
b10110111 C
b0 B
b10111100 C
0)
1'
1$
#3800
b111101100110010011000000 !
0@
0?
0>
1;
09
17
06
02
10
0.
1*
b0 C
b11110110 B
b111101 B
b111101 C
b111 B
b1000100 C
b11 B
b1000111 C
b1100100 B
b110010 B
b1111001 C
b110 B
b1111111 C
b1 B
b10000000 C
b0 B
b11000000 B
b1100 B
b10001100 C
b110 B
b10010010 C
b11 B
b10010101 C
b0 B
b10011010 C
1(
0'
0$
#3900
b110010110001100110010111 !
1A
1@
1?
1=
0;
19
07
16
15
04
03
11
0/
1.
0-
0,
b0 C
b11001011 B
b110010 B
b110010 C
b110 B
b111000 C
b11 B
b111011 C
b11001 B
b1100 B
b1000111 C
b1 B
b1001000 C
b0 B
b10010111 B
b1001 B
b1010001 C
b100 B
b1010101 C
b10 B
b1010111 C
b0 B
b1011100 C
0(
1'
1#
0"
#4000
b110100011001000100100101 !
0@
0=
1<
0:
06
12
00
0.
1-
b0 C
b11010001 B
b110100 B
b110100 C
b110 B
b111010 C
b11 B
b111101 C
b10010001 B
b1001000 B
b10000101 C
b1001 B
b10001110 C
b10 B
b10010000 C
b1 B
b10010001 C
b100101 B
b10 B
b10010011 C
b1 B
b10010100 C
b0 B
b10011001 C
1)
0'
0#
1"
#4100
b11100111101101111000111 !
1@
0<
1;
1:
18
16
13
10
1,
0*
b0 C
b1110011 B
b11100 B
b11100 C
b11 B
b11111 C
b1 B
b100000 C
b11011011 B
b1101101 B
b10001101 C
b1101 B
b10011010 C
b11 B
b10011101 C
b1 B
b10011110 C
b11000111 B
b1100 B
b10101010 C
b110 B
b10110000 C
b11 B
b10110011 C
b0 B
b10111000 C
0)
1$
#4200
b110010110111001001011000 !
0A
0@
0?
1>
1=
0:
09
06
14
02
1.
0-
0,
1*
b0 C
b11001011 B
b110010 B
b110010 C
b110 B
b111000 C
b11 B
b111011 C
b1110010 B
b111001 B
b1110100 C
b111 B
b1111011 C
b1 B
b1111100 C
b0 B
b1011000 B
b101 B
b10000001 C
b10 B
b10000011 C
b1 B
b10000100 C
b0 B
b10001001 C
1)
0%
0$
#4300
b101111111111100101010001 !
1A
0>
19
08
16
12
1/
1-
1,
0+
b0 C
b10111111 B
b101111 B
b101111 C
b101 B
b110100 C
b10 B
b110110 C
b11111001 B
b1111100 B
b10110010 C
b1111 B
b11000001 C
b11 B
b11000100 C
b1 B
b11000101 C
b1010001 B
b101 B
b11001010 C
b10 B
b11001100 C
b1 B
b11001101 C
b0 B
b11010010 C
0)
1(
0&
1%
1#
#4400
b11100101100100100110010 !
0A
1@
1<
0;
05
04
01
0/
0.
1+
0*
b0 C
b1110010 B
b11100 B
b11100 C
b11 B
b11111 C
b1 B
b100000 C
b11001001 B
b1100100 B
b10000100 C
b1100 B
b10010000 C
b11 B
b10010011 C
b1 B
b10010100 C
b110010 B
b11 B
b10010111 C
b1 B
b10011000 C
b0 B
b10011101 C
1)
0(
1'
1&
0#
#4500
b1000001101111000100011 !
1A
0=
09
18
17
15
00
0-
0+
b0 C
b100000 B
b1000 B
b1000 C
b1 B
b1001 C
b0 B
b11011110 B
b1101111 B
b1111000 C
b1101 B
b10000101 C
b11 B
b10001000 C
b1 B
b10001001 C
b100011 B
b10 B
b10001011 C
b1 B
b10001100 C
b0 B
b10010001 C
0'
0&
#4600
b101101001101010100 !
0A
0@
1?
1=
0<
1;
19
07
06
10
0,
b0 C
b10 B
b0 B
b11010011 B
b1101001 B
b1101001 C
b1101 B
b1110110 C
b11 B
b1111001 C
b1 B
b1111010 C
b1010100 B
b101 B
b1111111 C
b10 B
b10000001 C
b1 B
b10000010 C
b0 B
b10000111 C
1(
1'
0%
#4700
b101000010000000110110011 !
1A
1@
0?
1<
0;
1:
08
05
03
02
11
00
1,
1*
b0 C
b10100001 B
b101000 B
b101000 C
b101 B
b101101 C
b10 B
b101111 C
b1 B
b0 B
b10110011 B
b1011 B
b111010 C
b101 B
b111111 C
b10 B
b1000001 C
b0 B
b1000110 C
0)
1#
0"
#4800
b111100101011001011010 !
0A
1>
0<
1;
0:
09
18
17
15
13
01
10
1/
1.
1-
0,
0*
b0 C
b11110 B
b111 B
b111 C
b0 B
b1010110 B
b101011 B
b110010 C
b101 B
b110111 C
b1 B
b111000 C
b0 B
b1011010 B
b101 B
b111101 C
b10 B
b111111 C
b1 B
b1000000 C
b0 B
b1000101 C
1)
0(
#4900
b101011100001101011100110 !
1?
0>
0=
1<
1:
07
16
03
0-
1,
1*
b0 C
b10101110 B
b101011 B
b101011 C
b101 B
b110000 C
b10 B
b110010 C
b11010 B
b1101 B
b111111 C
b1 B
b1000000 C
b0 B
b11100110 B
b1110 B
b1001110 C
b111 B
b1010101 C
b11 B
b1011000 C
b0 B
b1011101 C
1&
1%
#5000
b110101101111010111110110 !
1=
19
08
17
06
14
13
12
0.
1-
0,
1+
b0 C
b11010110 B
b110101 B
b110101 C
b110 B
b111011 C
b11 B
b111110 C
b11110101 B
b1111010 B
b10111000 C
b1111 B
b11000111 C
b11 B
b11001010 C
b1 B
b11001011 C
b11110110 B
b1111 B
b11011010 C
b111 B
b11100001 C
b11 B
b11100100 C
b0 B
b11101001 C
0'
0%
1$
1"
#5100
b110101100011001001100101 !
1A
0@
0=
0:
09
18
07
03
02
b0 C
b11010110 B
b110101 B
b110101 C
b110 B
b111011 C
b11 B
b111110 C
b110010 B
b11001 B
b1010111 C
b11 B
b1011010 C
b0 B
b1100101 B
b110 B
b1100000 C
b11 B
b1100011 C
b1 B
b1100100 C
b0 B
b1101001 C
0"
#5200
b111110100001010111101010 !
0A
1@
0?
1>
1:
19
08
17
04
0/
1.
1,
b0 C
b11111010 B
b111110 B
b111110 C
b111 B
b1000101 C
b11 B
b1001000 C
b10101 B
b1010 B
b1010010 C
b1 B
b1010011 C
b0 B
b11101010 B
b1110 B
b1100001 C
b111 B
b1101000 C
b11 B
b1101011 C
b0 B
b1110000 C
0)
0&
1%
#5300
b10100110101101100001111 !
1A
1?
0<
0;
0:
18
07
16
13
11
0.
0,
0*
b0 C
b1010011 B
b10100 B
b10100 C
b10 B
b10110 C
b1 B
b10111 C
b1011011 B
b101101 B
b1000100 C
b101 B
b1001001 C
b1 B
b1001010 C
b0 B
b1111 B
b0 B
b1001111 C
1)
1(
1'
1&
0%
0$
#5400
b11000001000011101111 !
1<
1;
1:
09
08
06
03
01
00
1/
1.
0-
0+
b0 C
b1100 B
b11 B
b11 C
b0 B
b10000 B
b1000 B
b1011 C
b1 B
b1100 C
b0 B
b11101111 B
b1110 B
b11010 C
b111 B
b100001 C
b11 B
b100100 C
b0 B
b101001 C
0(
0'
1$
0#
#5500
b100111001010010001000100 !
0A
0@
0>
0<
0:
17
05
14
12
1-
1*
b0 C
b10011100 B
b100111 B
b100111 C
b100 B
b101011 C
b10 B
b101101 C
b10100100 B
b1010010 B
b1111111 C
b1010 B
b10001001 C
b10 B
b10001011 C
b1 B
b10001100 C
b1000100 B
b100 B
b10010000 C
b10 B
b10010010 C
b1 B
b10010011 C
b0 B
b10011000 C
0)
1%
0$
1"
#5600
b110100100101110111001001 !
1A
0?
1>
1:
19
16
15
04
13
02
10
0/
0.
1+
b0 C
b11010010 B
b110100 B
b110100 C
b110 B
b111010 C
b11 B
b111101 C
b1011101 B
b101110 B
b1101011 C
b101 B
b1110000 C
b1 B
b1110001 C
b0 B
b11001001 B
b1100 B
b1111101 C
b110 B
b10000011 C
b11 B
b10000110 C
b0 B
b10001011 C
1)
1(
0%
#5700
b111011110001000011001011 !
1@
09
07
06
03
11
1/
1.
0-
1,
b0 C
b11101111 B
b111011 B
b111011 C
b111 B
b1000010 C
b11 B
b1000101 C
b10000 B
b1000 B
b1001101 C
b1 B
b1001110 C
b0 B
b11001011 B
b1100 B
b1011010 C
b110 B
b1100000 C
b11 B
b1100011 C
b0 B
b1101000 C
0)
0(
1$
1#
0"
#5800
b100111101100001101000111 !
1?
0>
0:
19
18
05
13
12
01
1-
0,
0+
b0 C
b10011110 B
b100111 B
b100111 C
b100 B
b101011 C
b10 B
b101101 C
b11000011 B
b1100001 B
b10001110 C
b1100 B
b10011010 C
b11 B
b10011101 C
b1 B
b10011110 C
b1000111 B
b100 B
b10100010 C
b10 B
b10100100 C
b1 B
b10100101 C
b0 B
b10101010 C
1(
0#
1"
#5900
b101000110111101011000111 !
1:
09
16
15
14
02
11
0/
0.
0-
1,
b0 C
b10100011 B
b101000 B
b101000 C
b101 B
b101101 C
b10 B
b101111 C
b1111010 B
b111101 B
b1101100 C
b111 B
b1110011 C
b1 B
b1110100 C
b0 B
b11000111 B
b1100 B
b10000000 C
b110 B
b10000110 C
b11 B
b10001001 C
b0 B
b10001110 C
1'
0$
#6000
b101000001101010111110010 !
0A
0?
1=
1<
19
08
17
06
04
12
01
00
b0 C
b10100000 B
b101000 B
b101000 C
b101 B
b101101 C
b10 B
b101111 C
b11010101 B
b1101010 B
b10011001 C
b1101 B
b10100110 C
b11 B
b10101001 C
b1 B
b10101010 C
b11110010 B
b1111 B
b10111001 C
b111 B
b11000000 C
b11 B
b11000011 C
b0 B
b11001000 C
0(
0'
1#
#6100
b1110101001101111100001 !
1A
0@
0=
18
07
16
03
10
1.
1-
0*
b0 C
b111010 B
b1110 B
b1110 C
b1 B
b1111 C
b0 B
b10011011 B
b1001101 B
b1011100 C
b1001 B
b1100101 C
b10 B
b1100111 C
b1 B
b1101000 C
b11100001 B
b1110 B
b1110110 C
b111 B
b1111101 C
b11 B
b10000000 C
b0 B
b10000101 C
1)
1'
0&
0#
#6200
b100110100101001110000101 !
1?
0<
0;
06
13
02
0,
1*
b0 C
b10011010 B
b100110 B
b100110 C
b100 B
b101010 C
b10 B
b101100 C
b1010011 B
b101001 B
b1010101 C
b101 B
b1011010 C
b1 B
b1011011 C
b0 B
b10000101 B
b1000 B
b1100011 C
b100 B
b1100111 C
b10 B
b1101001 C
b0 B
b1101110 C
0)
1(
1&
1$
1#
0"
#6300
b1010011101001100110000 !
0A
0?
1=
1<
0:
12
11
00
0-
1,
0*
b0 C
b101001 B
b1010 B
b1010 C
b1 B
b1011 C
b0 B
b11010011 B
b1101001 B
b1110100 C
b1101 B
b10000001 C
b11 B
b10000100 C
b1 B
b10000101 C
b110000 B
b11 B
b10001000 C
b1 B
b10001001 C
b0 B
b10001110 C
0$
0#
1"
#6400
b111101000010001001110110 !
1@
1?
1;
09
05
14
03
02
01
1/
0.
1-
1+
1*
b0 C
b11110100 B
b111101 B
b111101 C
b111 B
b1000100 C
b11 B
b1000111 C
b100010 B
b10001 B
b1011000 C
b10 B
b1011010 C
b0 B
b1110110 B
b111 B
b1100001 C
b11 B
b1100100 C
b1 B
b1100101 C
b0 B
b1101010 C
0'
1$
1#
0"
