RGB-Y Floating Point Modules/fp_rgb2grey_shifting/fp_rgb2grey_shifting.v
module fp_rgb2grey_shifting(
  input [47:0] rgb_pixel,
  output [15:0] grey_pixel
);
  reg [4:0] redc_exp, greenc_exp, bluec_exp;
  reg [10:0] redw_sig, greenw_sig, bluew_sig, temp;
  reg [4:0] redw_exp, greenw_exp, bluew_exp;
  reg [4:0] augend_exp0, shift0, augend_exp1, shift1;
  reg [10:0] augend_sig0, addend_sig0, sum_sig0, augend_sig1, addend_sig1, sum_sig1;
  reg carry0, carry1;

  always @(*) begin
    {redw_sig, greenw_sig, bluew_sig} = 33'd0;
    
    redc_exp = 5'b01101;
    greenc_exp = 5'b01110;
    bluec_exp = 5'b01011;    

    //red constant shifting multiplier
    temp = {1'b1, rgb_pixel[41:32]};
    temp = temp >> 1;
    redw_sig = redw_sig + temp;
    temp = temp >> 3;
    redw_sig = redw_sig + temp;
    temp = temp >> 1;
    redw_sig = redw_sig + temp;
    temp = temp >> 3;
    redw_sig = redw_sig + temp;
    temp = temp >> 3;
    redw_sig = redw_sig + temp;

    //green constant shifting multiplier
    temp = {1'b1, rgb_pixel[25:16]};
    temp = temp >> 1;
    greenw_sig = greenw_sig + temp;
    temp = temp >> 3;
    greenw_sig = greenw_sig + temp;
    temp = temp >> 2;
    greenw_sig = greenw_sig + temp;
    temp = temp >> 1;
    greenw_sig = greenw_sig + temp;
    temp = temp >> 3;
    greenw_sig = greenw_sig + temp;

    //blue constant shifting multiplier
    temp = {1'b1, rgb_pixel[9:0]};
    temp = temp >> 1;
    bluew_sig = bluew_sig + temp;
    temp = temp >> 1;
    bluew_sig = bluew_sig + temp;
    temp = temp >> 1;
    bluew_sig = bluew_sig + temp;
    temp = temp >> 2;
    bluew_sig = bluew_sig + temp;
    temp = temp >> 3;
    bluew_sig = bluew_sig + temp;
    temp = temp >> 1;
    bluew_sig = bluew_sig + temp;

    redw_exp = rgb_pixel[46:42] - 14 + redc_exp;
    greenw_exp = rgb_pixel[30:26] - 14 + greenc_exp;
    bluew_exp = rgb_pixel[14:10] - 14 + bluec_exp;

    if (redw_exp < greenw_exp) begin //green > red
      augend_sig0 = greenw_sig;
      addend_sig0 = redw_sig;
      augend_exp0 = greenw_exp;
      shift0 = greenw_exp - redw_exp;
    end else begin //red > green
      augend_sig0 = redw_sig;
      addend_sig0 = greenw_sig;
      augend_exp0 = redw_exp;
      shift0 = redw_exp - greenw_exp;
    end
    addend_sig0 = addend_sig0 >> shift0;
    {carry0,sum_sig0} = augend_sig0 + addend_sig0;
    if (carry0) begin
      sum_sig0 = sum_sig0 >> 1;
      augend_exp0 = augend_exp0 + 1'b1;
    end
    
    if (bluew_exp < augend_exp0) begin
      augend_sig1 = sum_sig0;
      addend_sig1 = bluew_sig;
      augend_exp1 = augend_exp0;
      shift1 = augend_exp0 - bluew_exp;
    end else begin
      augend_sig1 = bluew_sig;
      addend_sig1 = sum_sig0;
      augend_exp1 = bluew_exp;
      shift1 = bluew_exp - augend_exp0;
    end
    addend_sig1 = addend_sig1 >> shift1;
    {carry1, sum_sig1} = augend_sig1 + addend_sig1;
    if (carry1) begin
      sum_sig1 = sum_sig1 >> 1;
      augend_exp1 = augend_exp1 + 1'b1;
    end

  end
  assign grey_pixel = {1'b0, augend_exp1, sum_sig1[9:0]};
endmodule

RGB-Y Floating Point Modules/fp_rgb2grey_tb/fp_rgb2grey_tb.v
`include "fp_rgb2grey_shifting.v"

module fp_rgb2grey_tb;
  reg [47:0] rgb_pixel;
  wire [15:0] grey_pixel;
  fp_rgb2grey_shifting uut(.rgb_pixel(rgb_pixel), .grey_pixel(grey_pixel));
  initial begin
    $dumpfile("fp_rgb2grey_shifting.vcd");
    $dumpvars(0, fp_rgb2grey_tb);
    repeat (1000) begin
      rgb_pixel[47] = 1'b0; //always positive
      rgb_pixel[46:42] = $urandom_range(15, 22); //exp of numbers between 0 and 255
      rgb_pixel[41:32] = $urandom_range(0, 1023); //2^10-1
      rgb_pixel[31] = 1'b0;
      rgb_pixel[30:26] = $urandom_range(15, 22);
      rgb_pixel[25:16] = $urandom_range(0, 1023);
      rgb_pixel[15] = 1'b0;
      rgb_pixel[14:10] = $urandom_range(15, 22);
      rgb_pixel[9:0] = $urandom_range(0, 1023);
      #100;
    end
  end
endmodule

RGB-Y Floating Point Modules/fp_rgb2grey_shifting/fp_rgb2grey_shifting.vcd
$date
	Sat Mar 02 22:38:46 2024
$end
$version
	ModelSim Version 10.5b
$end
$timescale
	1ps
$end

$scope module fp_rgb2grey_tb $end
$var reg 48 ! rgb_pixel [47:0] $end
$var wire 1 " grey_pixel [15] $end
$var wire 1 # grey_pixel [14] $end
$var wire 1 $ grey_pixel [13] $end
$var wire 1 % grey_pixel [12] $end
$var wire 1 & grey_pixel [11] $end
$var wire 1 ' grey_pixel [10] $end
$var wire 1 ( grey_pixel [9] $end
$var wire 1 ) grey_pixel [8] $end
$var wire 1 * grey_pixel [7] $end
$var wire 1 + grey_pixel [6] $end
$var wire 1 , grey_pixel [5] $end
$var wire 1 - grey_pixel [4] $end
$var wire 1 . grey_pixel [3] $end
$var wire 1 / grey_pixel [2] $end
$var wire 1 0 grey_pixel [1] $end
$var wire 1 1 grey_pixel [0] $end

$scope module uut $end
$var wire 1 2 rgb_pixel [47] $end
$var wire 1 3 rgb_pixel [46] $end
$var wire 1 4 rgb_pixel [45] $end
$var wire 1 5 rgb_pixel [44] $end
$var wire 1 6 rgb_pixel [43] $end
$var wire 1 7 rgb_pixel [42] $end
$var wire 1 8 rgb_pixel [41] $end
$var wire 1 9 rgb_pixel [40] $end
$var wire 1 : rgb_pixel [39] $end
$var wire 1 ; rgb_pixel [38] $end
$var wire 1 < rgb_pixel [37] $end
$var wire 1 = rgb_pixel [36] $end
$var wire 1 > rgb_pixel [35] $end
$var wire 1 ? rgb_pixel [34] $end
$var wire 1 @ rgb_pixel [33] $end
$var wire 1 A rgb_pixel [32] $end
$var wire 1 B rgb_pixel [31] $end
$var wire 1 C rgb_pixel [30] $end
$var wire 1 D rgb_pixel [29] $end
$var wire 1 E rgb_pixel [28] $end
$var wire 1 F rgb_pixel [27] $end
$var wire 1 G rgb_pixel [26] $end
$var wire 1 H rgb_pixel [25] $end
$var wire 1 I rgb_pixel [24] $end
$var wire 1 J rgb_pixel [23] $end
$var wire 1 K rgb_pixel [22] $end
$var wire 1 L rgb_pixel [21] $end
$var wire 1 M rgb_pixel [20] $end
$var wire 1 N rgb_pixel [19] $end
$var wire 1 O rgb_pixel [18] $end
$var wire 1 P rgb_pixel [17] $end
$var wire 1 Q rgb_pixel [16] $end
$var wire 1 R rgb_pixel [15] $end
$var wire 1 S rgb_pixel [14] $end
$var wire 1 T rgb_pixel [13] $end
$var wire 1 U rgb_pixel [12] $end
$var wire 1 V rgb_pixel [11] $end
$var wire 1 W rgb_pixel [10] $end
$var wire 1 X rgb_pixel [9] $end
$var wire 1 Y rgb_pixel [8] $end
$var wire 1 Z rgb_pixel [7] $end
$var wire 1 [ rgb_pixel [6] $end
$var wire 1 \ rgb_pixel [5] $end
$var wire 1 ] rgb_pixel [4] $end
$var wire 1 ^ rgb_pixel [3] $end
$var wire 1 _ rgb_pixel [2] $end
$var wire 1 ` rgb_pixel [1] $end
$var wire 1 a rgb_pixel [0] $end
$var wire 1 " grey_pixel [15] $end
$var wire 1 # grey_pixel [14] $end
$var wire 1 $ grey_pixel [13] $end
$var wire 1 % grey_pixel [12] $end
$var wire 1 & grey_pixel [11] $end
$var wire 1 ' grey_pixel [10] $end
$var wire 1 ( grey_pixel [9] $end
$var wire 1 ) grey_pixel [8] $end
$var wire 1 * grey_pixel [7] $end
$var wire 1 + grey_pixel [6] $end
$var wire 1 , grey_pixel [5] $end
$var wire 1 - grey_pixel [4] $end
$var wire 1 . grey_pixel [3] $end
$var wire 1 / grey_pixel [2] $end
$var wire 1 0 grey_pixel [1] $end
$var wire 1 1 grey_pixel [0] $end
$var reg 5 b redc_exp [4:0] $end
$var reg 5 c greenc_exp [4:0] $end
$var reg 5 d bluec_exp [4:0] $end
$var reg 11 e redw_sig [10:0] $end
$var reg 11 f greenw_sig [10:0] $end
$var reg 11 g bluew_sig [10:0] $end
$var reg 11 h temp [10:0] $end
$var reg 5 i redw_exp [4:0] $end
$var reg 5 j greenw_exp [4:0] $end
$var reg 5 k bluew_exp [4:0] $end
$var reg 5 l augend_exp0 [4:0] $end
$var reg 5 m shift0 [4:0] $end
$var reg 5 n augend_exp1 [4:0] $end
$var reg 5 o shift1 [4:0] $end
$var reg 11 p augend_sig0 [10:0] $end
$var reg 11 q addend_sig0 [10:0] $end
$var reg 11 r sum_sig0 [10:0] $end
$var reg 11 s augend_sig1 [10:0] $end
$var reg 11 t addend_sig1 [10:0] $end
$var reg 11 u sum_sig1 [10:0] $end
$var reg 1 v carry0 $end
$var reg 1 w carry1 $end
$upscope $end
$upscope $end
$enddefinitions $end
#0
$dumpvars
b1111000010011001010111101101100101011001000110 !
b1101 b
b1110 c
b1011 d
b1001111010 e
b10010000100 f
b10110110111 g
b11 h
b1110 i
b10101 j
b10010 k
b10101 l
b111 m
b10101 n
b11 o
b10010000100 p
b100 q
b10010001000 r
b10010001000 s
b10110110 t
b10100111110 u
0v
0w
01
10
1/
1.
1-
1,
0+
0*
1)
0(
1'
0&
1%
0$
1#
0"
0a
1`
1_
0^
0]
0\
1[
0Z
0Y
1X
1W
0V
1U
0T
1S
0R
0Q
1P
1O
0N
1M
1L
0K
1J
1I
1H
1G
0F
1E
0D
1C
0B
0A
1@
1?
0>
0=
1<
0;
0:
09
08
17
16
15
14
03
02
$end
#100
b10001000010011001010111101101100101011001000110 !
b10001110010111001010111101101100101011001000110 !
b10001110010111001011011101101100101011001000110 !
b10001110010111001011001001110100101011001000110 !
b10001110010111001011001001110100100011001000110 !
b10001110010111001011001001110100100010110110100 !
0`
1]
1\
0[
1Z
1Y
0X
0U
0O
1N
0J
0H
0G
1F
1>
19
18
06
05
04
13
b0 g
b0 f
b0 e
b11100101110 h
b1110010111 h
b1110010111 e
b1110010 h
b10000001001 e
b111001 h
b10001000010 e
b111 h
b10001001001 e
b0 h
b10100111010 h
b1010011101 h
b1010011101 f
b1010011 h
b1011110000 f
b10100 h
b1100000100 f
b1010 h
b1100001110 f
b1 h
b1100001111 f
b10110110100 h
b1011011010 h
b1011011010 g
b101101101 h
b10001000111 g
b10110110 h
b10011111101 g
b101101 h
b10100101010 g
b101 h
b10100101111 g
b10 h
b10100110001 g
b10000 i
b10110 j
b1110 k
b1100001111 p
b10001001001 q
b10110 l
b110 m
b10001 q
b1100100000 r
b1100100000 s
b10100110001 t
b10110 n
b1000 o
b101 t
b1100100101 u
11
00
0.
0-
1(
0'
1&
#200
b10110110010111001011001001110100100010110110100 !
b10110100101011001011001001110100100010110110100 !
b10110100101011001010001001110100100010110110100 !
b10110100101011001010011110101000100010110110100 !
b10110100101011001010011110101000101010110110100 !
b10110100101011001010011110101000101010101111101 !
1a
1^
1[
0Z
1U
0P
1O
0N
0L
1K
1J
1H
0F
0>
1=
0<
1;
09
07
16
15
b0 g
b0 f
b0 e
b11001010110 h
b1100101011 h
b1100101011 e
b1100101 h
b1110010000 e
b110010 h
b1111000010 e
b110 h
b1111001000 e
b0 h
b11111010100 h
b1111101010 h
b1111101010 f
b1111101 h
b10001100111 f
b11111 h
b10010000110 f
b1111 h
b10010010101 f
b1 h
b10010010110 f
b10101111101 h
b1010111110 h
b1010111110 g
b101011111 h
b10000011101 g
b10101111 h
b10011001100 g
b101011 h
b10011110111 g
b101 h
b10011111100 g
b10 h
b10011111110 g
b10101 i
b10100 j
b10010 k
b1111001000 p
b10010010110 q
b10101 l
b1 m
b1001001011 q
b11000010011 r
b11000010011 s
b10011111110 t
b10101 n
b11 o
b10011111 t
b11010110010 u
01
10
0/
1-
1*
0)
1'
0&
#300
b10010100101011001010011110101000101010101111101 !
b10010100000010101010011110101000101010101111101 !
b10010100000010101001011110101000101010101111101 !
b10010100000010101001011001000000101010101111101 !
b10010100000010101001011001000000101000101111101 !
b10010100000010101001011001000000101001100000101 !
0^
0]
0\
0[
1X
0W
0O
0M
1L
0K
0J
1F
0E
1A
0@
0=
0;
05
b0 g
b0 f
b0 e
b11000000101 h
b1100000010 h
b1100000010 e
b1100000 h
b1101100010 e
b110000 h
b1110010010 e
b110 h
b1110011000 e
b0 h
b11100100000 h
b1110010000 h
b1110010000 f
b1110010 h
b10000000010 f
b11100 h
b10000011110 f
b1110 h
b10000101100 f
b1 h
b10000101101 f
b11100000101 h
b1110000010 h
b1110000010 g
b111000001 h
b10101000011 g
b11100000 h
b11000100011 g
b111000 h
b11001011011 g
b111 h
b11001100010 g
b11 h
b11001100101 g
b10001 i
b10010 j
b10001 k
b10000101101 p
b1110011000 q
b10010 l
b111001100 q
b10111111001 r
b10111111001 s
b11001100101 t
b10010 n
b1 o
b1100110010 t
b100101011 u
1w
b10010101 u
b10011 n
11
00
1/
0,
0(
1&
0%
#400
b10100100000010101001011001000000101001100000101 !
b10100101110100101001011001000000101001100000101 !
b10100101110100101010011001000000101001100000101 !
b10100101110100101010001100010100101001100000101 !
b10100101110100101010001100010100011111100000101 !
b10100101110100101010001100010100011110110001011 !
1`
0_
1^
1Z
0X
1W
1V
1T
0S
1P
1N
0L
1J
0H
0F
1E
0?
1>
1<
1;
1:
06
15
b0 g
b0 f
b0 e
b11011101001 h
b1101110100 h
b1101110100 e
b1101110 h
b1111100010 e
b110111 h
b10000011001 e
b110 h
b10000011111 e
b0 h
b10110001010 h
b1011000101 h
b1011000101 f
b1011000 h
b1100011101 f
b10110 h
b1100110011 f
b1011 h
b1100111110 f
b1 h
b1100111111 f
b10110001011 h
b1011000101 h
b1011000101 g
b101100010 h
b10000100111 g
b10110001 h
b10011011000 g
b101100 h
b10100000100 g
b101 h
b10100001001 g
b10 h
b10100001011 g
b10011 i
b10100 j
b1100 k
b1100111111 p
b10000011111 q
b10100 l
b1000001111 q
b10101001110 r
b10101001110 s
b10100001011 t
b10100 n
b1000 o
b101 t
b10101010011 u
0w
10
0/
1+
0*
1)
0'
0&
1%
#500
b10101101110100101010001100010100011110110001011 !
b10101111100100101010001100010100011110110001011 !
b10101111100100101000001100010100011110110001011 !
b10101111100100101000001010000000011110110001011 !
b10101111100100101000001010000000011111000001110 !
0a
1_
0Z
0Y
1X
0P
0N
1K
0J
0E
0<
19
17
b0 g
b0 f
b0 e
b11111001001 h
b1111100100 h
b1111100100 e
b1111100 h
b10001100000 e
b111110 h
b10010011110 e
b111 h
b10010100101 e
b0 h
b10101000000 h
b1010100000 h
b1010100000 f
b1010100 h
b1011110100 f
b10101 h
b1100001001 f
b1010 h
b1100010011 f
b1 h
b1100010100 f
b11000001110 h
b1100000111 h
b1100000111 g
b110000011 h
b10010001010 g
b11000001 h
b10101001011 g
b110000 h
b10101111011 g
b110 h
b10110000001 g
b11 h
b10110000100 g
b10100 i
b10000 j
b10010100101 p
b1100010100 q
b100 m
b110001 q
b10011010110 r
b10011010110 s
b10110000100 t
b101 t
b10011011011 u
1.
1*
0)
#600
b10011111100100101000001010000000011111000001110 !
b10011011000111001000001010000000011111000001110 !
b10011011000111000111101010000000011111000001110 !
b10011011000111000111101100101110011111000001110 !
b10011011000111000111101100101110101001000001110 !
b10011011000111000111101100101110101001111000111 !
1a
0^
1[
1Z
1Y
0W
0V
0T
1S
1Q
1P
1O
1M
0K
1J
1G
1F
1E
1D
0C
0A
1@
1?
0;
08
16
05
b0 g
b0 f
b0 e
b10110001110 h
b1011000111 h
b1011000111 e
b1011000 h
b1100011111 e
b101100 h
b1101001011 e
b101 h
b1101010000 e
b0 h
b10110010111 h
b1011001011 h
b1011001011 f
b1011001 h
b1100100100 f
b10110 h
b1100111010 f
b1011 h
b1101000101 f
b1 h
b1101000110 f
b11111000111 h
b1111100011 h
b1111100011 g
b111110001 h
b10111010100 g
b11111000 h
b11011001100 g
b111110 h
b11100001010 g
b111 h
b11100010001 g
b11 h
b11100010100 g
b10010 i
b1111 j
b10001 k
b1101010000 p
b1101000110 q
b10010 l
b11 m
b1101000 q
b1110111000 r
b1110111000 s
b11100010100 t
b10010 n
b1 o
b1110001010 t
b11101000010 u
01
0.
0-
0*
1)
1(
1&
0%
#700
b1111011000111000111101100101110101001111000111 !
b1111010101000100111101100101110101001111000111 !
b1111010101000101000101100101110101001111000111 !
b1111010101000101000110001000110101001111000111 !
b1111010101000101000110001000110100111111000111 !
b1111010101000101000110001000110100110110110011 !
0_
1]
1\
0[
0X
1W
1V
0U
0O
0M
1L
0J
0I
1H
0F
0E
0D
1C
1A
0@
0?
0>
1=
1;
0:
15
14
03
b0 g
b0 f
b0 e
b10101010001 h
b1010101000 h
b1010101000 e
b1010101 h
b1011111101 e
b101010 h
b1100100111 e
b101 h
b1100101100 e
b0 h
b11000100011 h
b1100010001 h
b1100010001 f
b1100010 h
b1101110011 f
b11000 h
b1110001011 f
b1100 h
b1110010111 f
b1 h
b1110011000 f
b10110110011 h
b1011011001 h
b1011011001 g
b101101100 h
b10001000101 g
b10110110 h
b10011111011 g
b101101 h
b10100101000 g
b101 h
b10100101101 g
b10 h
b10100101111 g
b1110 i
b10001 j
b10000 k
b1110011000 p
b1100101100 q
b10001 l
b1100101 q
b1111111101 r
b1111111101 s
b10100101111 t
b10001 n
b1010010111 t
b11010010100 u
00
1/
1-
0+
1*
0)
1'
0&
#800
b10001010101000101000110001000110100110110110011 !
b10001101110011001000110001000110100110110110011 !
b10001101110011001010110001000110100110110110011 !
b10001101110011001010110011001010100110110110011 !
b10001101110011001010110011001010100010110110011 !
b10001101110011001010110011001010100011100001111 !
1_
1^
0]
0\
0Z
1X
0V
0P
1O
1K
1E
0A
1@
1?
0=
1<
1:
09
18
06
05
04
13
b0 g
b0 f
b0 e
b11011100110 h
b1101110011 h
b1101110011 e
b1101110 h
b1111100001 e
b110111 h
b10000011000 e
b110 h
b10000011110 e
b0 h
b11001100101 h
b1100110010 h
b1100110010 f
b1100110 h
b1110011000 f
b11001 h
b1110110001 f
b1100 h
b1110111101 f
b1 h
b1110111110 f
b11100001111 h
b1110000111 h
b1110000111 g
b111000011 h
b10101001010 g
b11100001 h
b11000101011 g
b111000 h
b11001100011 g
b111 h
b11001101010 g
b11 h
b11001101101 g
b10000 i
b10101 j
b1110 k
b1110111110 p
b10000011110 q
b10101 l
b101 m
b100000 q
b1111011110 r
b1111011110 s
b11001101101 t
b10101 n
b111 o
b1100 t
b1111101010 u
10
0/
1.
0-
1,
1+
1)
1%
#900
b10110101110011001010110011001010100011100001111 !
b10110000100010001010110011001010100011100001111 !
b10110000100010001000010011001010100011100001111 !
b10110000100010001000000110010110100011100001111 !
b10110000100010001000000110010110101101100001111 !
b10110000100010001000000110010110101101011000111 !
0^
1[
1Z
0Y
0W
1V
1U
1P
0O
1N
0L
1J
0H
0G
0E
0@
0<
0:
08
07
16
15
b0 g
b0 f
b0 e
b10001000100 h
b1000100010 h
b1000100010 e
b1000100 h
b1001100110 e
b100010 h
b1010001000 e
b100 h
b1010001100 e
b0 h
b10011001011 h
b1001100101 h
b1001100101 f
b1001100 h
b1010110001 f
b10011 h
b1011000100 f
b1001 h
b1011001101 f
b1 h
b1011001110 f
b11011000111 h
b1101100011 h
b1101100011 g
b110110001 h
b10100010100 g
b11011000 h
b10111101100 g
b110110 h
b11000100010 g
b110 h
b11000101000 g
b11 h
b11000101011 g
b10101 i
b10000 j
b10011 k
b1010001100 p
b1011001110 q
b10110 q
b1010100010 r
b1010100010 s
b11000101011 t
b10 o
b110001010 t
b10000101100 u
00
1/
0+
0*
0)
0(
#1000
b10001000100010001000000110010110101101011000111 !
b10001111110000101000000110010110101101011000111 !
b10001111110000101010000110010110101101011000111 !
b10001111110000101010011001100000101101011000111 !
b10001111110000101010011001100000101011011000111 !
b10001111110000101010011001100000101010100011101 !
0`
1^
1]
0[
0Z
1Y
0X
1W
0V
0Q
0P
0N
1M
1L
0K
0J
1I
1H
1E
1A
0?
1<
1:
19
18
17
06
05
b0 g
b0 f
b0 e
b11111100001 h
b1111110000 h
b1111110000 e
b1111110 h
b10001101110 e
b111111 h
b10010101101 e
b111 h
b10010110100 e
b0 h
b11100110000 h
b1110011000 h
b1110011000 f
b1110011 h
b10000001011 f
b11100 h
b10000100111 f
b1110 h
b10000110101 f
b1 h
b10000110110 f
b10100011101 h
b1010001110 h
b1010001110 g
b101000111 h
b1111010101 g
b10100011 h
b10001111000 g
b101000 h
b10010100000 g
b101 h
b10010100101 g
b10 h
b10010100111 g
b10000 i
b10100 j
b10010 k
b10000110110 p
b10010110100 q
b10100 l
b100 m
b1001011 q
b10010000001 r
b10010000001 s
b10010100111 t
b10100 n
b100101001 t
b10110101010 u
10
0/
1*
1)
0'
#1100
b10001110001011001010011001100000101010100011101 !
b10001110001011001001011001100000101010100011101 !
b10001110001011001001011010000000101010100011101 !
b10001110001011001001011010000000101000100011101 !
b10001110001011001001011010000000101001010010001 !
0_
0^
1Z
0Y
1X
0W
0M
0L
1K
1F
0E
0A
1@
1?
1=
0<
0;
0:
b0 g
b0 f
b0 e
b11100010110 h
b1110001011 h
b1110001011 e
b1110001 h
b1111111100 e
b111000 h
b10000110100 e
b111 h
b10000111011 e
b0 h
b11101000000 h
b1110100000 h
b1110100000 f
b1110100 h
b10000010100 f
b11101 h
b10000110001 f
b1110 h
b10000111111 f
b1 h
b10001000000 f
b11010010001 h
b1101001000 h
b1101001000 g
b110100100 h
b10011101100 g
b11010010 h
b10110111110 g
b110100 h
b10111110010 g
b110 h
b10111111000 g
b11 h
b10111111011 g
b10010 j
b10001 k
b10001000000 p
b10000111011 q
b10010 l
b10 m
b100001110 q
b10101001110 r
b10101001110 s
b10111111011 t
b10010 n
b1 o
b1011111101 t
b1001011 u
1w
b100101 u
b10011 n
11
00
1/
0.
0*
0)
1'
1&
0%
#1200
b10010110001011001001011010000000101001010010001 !
b10010001010000001001011010000000101001010010001 !
b10010001010000001011011010000000101001010010001 !
b10010001010000001011000000111010101001010010001 !
b10010001010000001011000000111010100111010010001 !
b10010001010000001011000000111010100111111011101 !
1_
1^
1[
1Y
1W
1V
0U
1Q
1O
1N
1M
0K
0I
0H
1E
0@
0?
0=
1<
1:
09
08
07
16
b0 g
b0 f
b0 e
b10010100000 h
b1001010000 h
b1001010000 e
b1001010 h
b1010011010 e
b100101 h
b1010111111 e
b100 h
b1011000011 e
b0 h
b10000011101 h
b1000001110 h
b1000001110 f
b1000001 h
b1001001111 f
b10000 h
b1001011111 f
b1000 h
b1001100111 f
b1 h
b1001101000 f
b11111011101 h
b1111101110 h
b1111101110 g
b111110111 h
b10111100101 g
b11111011 h
b11011100000 g
b111110 h
b11100011110 g
b111 h
b11100100101 g
b11 h
b11100101000 g
b10001 i
b10110 j
b10000 k
b1001101000 p
b1011000011 q
b10110 l
b101 m
b10110 q
b1001111110 r
b1001111110 s
b11100101000 t
b10110 n
b110 o
b11100 t
b1010011010 u
0w
01
10
0/
1.
1-
0,
1*
1(
0'
1%
#1300
b10001001010000001011000000111010100111111011101 !
b10001001000010001011000000111010100111111011101 !
b10001001000010001011000100010010100111111011101 !
b10001001000010001011000100010010100011111011101 !
b10001001000010001011000100010010100011011010101 !
0^
0Y
0V
0O
0M
1J
1?
0<
17
06
b0 g
b0 f
b0 e
b10010000100 h
b1001000010 h
b1001000010 e
b1001000 h
b1010001010 e
b100100 h
b1010101110 e
b100 h
b1010110010 e
b0 h
b10010001001 h
b1001000100 h
b1001000100 f
b1001000 h
b1010001100 f
b10010 h
b1010011110 f
b1001 h
b1010100111 f
b1 h
b1010101000 f
b11011010101 h
b1101101010 h
b1101101010 g
b110110101 h
b10100011111 g
b11011010 h
b10111111001 g
b110110 h
b11000101111 g
b110 h
b11000110101 g
b11 h
b11000111000 g
b10000 i
b1110 k
b1010101000 p
b1010110010 q
b110 m
b1010 q
b1010110010 r
b1010110010 s
b11000111000 t
b1000 o
b110 t
b1010111000 u
00
1,
#1400
b10101001000010001011000100010010100011011010101 !
b10101100100110001011000100010010100011011010101 !
b10101100100110001010100100010010100011011010101 !
b10101100100110001010110110000110100011011010101 !
b10101100100110001010110110000110011111011010101 !
b10101100100110001010110110000110011110110111100 !
0a
1^
1\
0[
1Y
0X
1V
1U
1T
0S
1P
0N
1K
1H
1G
0F
1>
1;
0:
18
15
b0 g
b0 f
b0 e
b11001001100 h
b1100100110 h
b1100100110 e
b1100100 h
b1110001010 e
b110010 h
b1110111100 e
b110 h
b1111000010 e
b0 h
b11011000011 h
b1101100001 h
b1101100001 f
b1101100 h
b1111001101 f
b11011 h
b1111101000 f
b1101 h
b1111110101 f
b1 h
b1111110110 f
b10110111100 h
b1011011110 h
b1011011110 g
b101101111 h
b10001001101 g
b10110111 h
b10100000100 g
b101101 h
b10100110001 g
b101 h
b10100110110 g
b10 h
b10100111000 g
b10100 i
b10101 j
b1100 k
b1111110110 p
b1111000010 q
b10101 l
b1 m
b111100001 q
b10111010111 r
b10111010111 s
b10100111000 t
b10101 n
b1001 o
b10 t
b10111011001 u
11
0,
1+
1)
0(
1'
0&
#1500
b10010100100110001010110110000110011110110111100 !
b10010101111001101010110110000110011110110111100 !
b10010101111001101011010110000110011110110111100 !
b10010101111001101011001101101110011110110111100 !
b10010101111001101011001101101110100100110111100 !
b10010101111001101011001101101110100101011100111 !
1a
1`
0^
0]
1[
0Y
1X
0W
0U
0T
1S
1O
1M
1L
0K
1I
0H
0G
1F
1A
1@
0?
0>
1=
1<
1:
07
16
05
b0 g
b0 f
b0 e
b11011110011 h
b1101111001 h
b1101111001 e
b1101111 h
b1111101000 e
b110111 h
b10000011111 e
b110 h
b10000100101 e
b0 h
b10110110111 h
b1011011011 h
b1011011011 f
b1011011 h
b1100110110 f
b10110 h
b1101001100 f
b1011 h
b1101010111 f
b1 h
b1101011000 f
b11011100111 h
b1101110011 h
b1101110011 g
b110111001 h
b10100101100 g
b11011100 h
b11000001000 g
b110111 h
b11000111111 g
b110 h
b11001000101 g
b11 h
b11001001000 g
b10001 i
b10110 j
b1111 k
b1101011000 p
b10000100101 q
b10110 l
b101 m
b100001 q
b1101111001 r
b1101111001 s
b11001001000 t
b10110 n
b111 o
b1100 t
b1110000101 u
1/
0.
0-
0+
1(
0'
1&
#1600
b1111101111001101011001101101110100101011100111 !
b1111010000100101011001101101110100101011100111 !
b1111010000100101000101101101110100101011100111 !
b1111010000100101000110110000010100101011100111 !
b1111010000100101000110110000010100111011100111 !
b1111010000100101000110110000010100111101100000 !
0a
0`
0_
0Z
1Y
1W
0P
0O
0M
0L
1K
0I
1H
1G
0F
0E
0@
1>
0=
0<
0;
0:
19
08
17
15
14
03
b0 g
b0 f
b0 e
b10100001001 h
b1010000100 h
b1010000100 e
b1010000 h
b1011010100 e
b101000 h
b1011111100 e
b101 h
b1100000001 e
b0 h
b11011000001 h
b1101100000 h
b1101100000 f
b1101100 h
b1111001100 f
b11011 h
b1111100111 f
b1101 h
b1111110100 f
b1 h
b1111110101 f
b11101100000 h
b1110110000 h
b1110110000 g
b111011000 h
b10110001000 g
b11101100 h
b11001110100 g
b111011 h
b11010101111 g
b111 h
b11010110110 g
b11 h
b11010111001 g
b1110 i
b10001 j
b10000 k
b1111110101 p
b1100000001 q
b10001 l
b11 m
b1100000 q
b10001010101 r
b10001010101 s
b11010111001 t
b10001 n
b1 o
b1101011100 t
b11110110001 u
0/
1-
1,
1'
0&
0%
#1700
b10110010000100101000110110000010100111101100000 !
b10110010110111101000110110000010100111101100000 !
b10110010110111101010010110000010100111101100000 !
b10110010110111101010011110011010100111101100000 !
b10110010110111101010011110011010100111011010000 !
1]
0\
1Z
0Y
1O
1N
1I
0G
1E
1@
1?
1<
1;
07
04
13
b0 g
b0 f
b0 e
b10101101111 h
b1010110111 h
b1010110111 e
b1010110 h
b1100001101 e
b101011 h
b1100111000 e
b101 h
b1100111101 e
b0 h
b11111001101 h
b1111100110 h
b1111100110 f
b1111100 h
b10001100010 f
b11111 h
b10010000001 f
b1111 h
b10010010000 f
b1 h
b10010010001 f
b11011010000 h
b1101101000 h
b1101101000 g
b110110100 h
b10100011100 g
b11011010 h
b10111110110 g
b110110 h
b11000101100 g
b110 h
b11000110010 g
b11 h
b11000110101 g
b10101 i
b10100 j
b1100111101 p
b10010010001 q
b10101 l
b1 m
b1001001000 q
b10110000101 r
b10110000101 s
b11000110101 t
b10101 n
b101 o
b110001 t
b10110110110 u
01
10
1/
0(
1%
#1800
b10000010110111101010011110011010100111011010000 !
b10000011111110001010011110011010100111011010000 !
b10000011111110001010000101001110100111011010000 !
b10000011111110001010000101001110100101011010000 !
b10000011111110001010000101001110100100010111110 !
1`
1_
1^
1\
0[
0X
0W
1P
0N
1L
0K
0I
0H
0A
0@
1=
1:
06
05
b0 g
b0 f
b0 e
b10111111100 h
b1011111110 h
b1011111110 e
b1011111 h
b1101011101 e
b101111 h
b1110001100 e
b101 h
b1110010001 e
b0 h
b10010100111 h
b1001010011 h
b1001010011 f
b1001010 h
b1010011101 f
b10010 h
b1010101111 f
b1001 h
b1010111000 f
b1 h
b1010111001 f
b10010111110 h
b1001011111 h
b1001011111 g
b100101111 h
b1110001110 g
b10010111 h
b10000100101 g
b100101 h
b10001001010 g
b100 h
b10001001110 g
b10 h
b10001010000 g
b1111 i
b1111 k
b1010111001 p
b1110010001 q
b10100 l
b101 m
b11100 q
b1011010101 r
b1011010101 s
b10001010000 t
b10100 n
b100010 t
b1011110111 u
11
1+
0)
1(
0'
