Gaussian Blur/GaussianBlur.v
module GaussianBlur(
  input [7:0] lu, cu, ru,
              lc, cc, rc,
              lb, cb, rb,
  output [7:0] blurred
);
  reg [9:0] cc4; //temp store after shift
  reg [8:0] lc2, cu2, rc2, cb2;
  reg [11:0] sum;
  always @(*) begin
      cc4 = cc;
      lc2 = lc;
      cu2 = cu;
      rc2 = rc;
      cb2 = cb;

      cc4 = cc4 << 2; //multiplying 4
      lc2 = lc2 << 1; //multiplying 2
      cu2 = cu2 << 1;
      rc2 = rc2 << 1;
      cb2 = cb2 << 1;

      sum = cc4 + lc2 + cu2 + rc2 + cb2 + lu + ru + lb + rb;
  end
  assign blurred = sum[11:4]; //dividing by 16
endmodule

Gaussian Blur/GaussianBlur_tb.v
`include "GaussianBlur.v"

module GaussianBlur_tb;
  reg [7:0] lu, cu, ru,
            lc, cc, rc,
            lb, cb, rb;
  wire [7:0] blurred;
  GaussianBlur uut(.lu(lu), .cu(cu), .ru(ru),
                   .lc(lc), .cc(cc), .rc(rc),
                   .lb(lb), .cb(cb), .rb(rb),
                   .blurred(blurred));
  initial begin
    $dumpfile("GuassianBlur.vcd");
    $dumpvars(0, GaussianBlur_tb);
    repeat (1000) begin
      lu = $urandom_range(0, 255);
      lc = $urandom_range(0, 255);
      lb = $urandom_range(0, 255);
      cu = $urandom_range(0, 255);
      cc = $urandom_range(0, 255);
      cb = $urandom_range(0, 255);
      ru = $urandom_range(0, 255);
      rc = $urandom_range(0, 255);
      rb = $urandom_range(0, 255);
      #100;
    end
  end
endmodule

Gaussian Blur/GuassianBlur.vcd
$date
	Fri Mar 15 03:06:54 2024
$end
$version
	ModelSim Version 10.5b
$end
$timescale
	1ps
$end

$scope module GaussianBlur_tb $end
$var reg 8 ! lu [7:0] $end
$var reg 8 " cu [7:0] $end
$var reg 8 # ru [7:0] $end
$var reg 8 $ lc [7:0] $end
$var reg 8 % cc [7:0] $end
$var reg 8 & rc [7:0] $end
$var reg 8 ' lb [7:0] $end
$var reg 8 ( cb [7:0] $end
$var reg 8 ) rb [7:0] $end
$var wire 1 * blurred [7] $end
$var wire 1 + blurred [6] $end
$var wire 1 , blurred [5] $end
$var wire 1 - blurred [4] $end
$var wire 1 . blurred [3] $end
$var wire 1 / blurred [2] $end
$var wire 1 0 blurred [1] $end
$var wire 1 1 blurred [0] $end

$scope module uut $end
$var wire 1 2 lu [7] $end
$var wire 1 3 lu [6] $end
$var wire 1 4 lu [5] $end
$var wire 1 5 lu [4] $end
$var wire 1 6 lu [3] $end
$var wire 1 7 lu [2] $end
$var wire 1 8 lu [1] $end
$var wire 1 9 lu [0] $end
$var wire 1 : cu [7] $end
$var wire 1 ; cu [6] $end
$var wire 1 < cu [5] $end
$var wire 1 = cu [4] $end
$var wire 1 > cu [3] $end
$var wire 1 ? cu [2] $end
$var wire 1 @ cu [1] $end
$var wire 1 A cu [0] $end
$var wire 1 B ru [7] $end
$var wire 1 C ru [6] $end
$var wire 1 D ru [5] $end
$var wire 1 E ru [4] $end
$var wire 1 F ru [3] $end
$var wire 1 G ru [2] $end
$var wire 1 H ru [1] $end
$var wire 1 I ru [0] $end
$var wire 1 J lc [7] $end
$var wire 1 K lc [6] $end
$var wire 1 L lc [5] $end
$var wire 1 M lc [4] $end
$var wire 1 N lc [3] $end
$var wire 1 O lc [2] $end
$var wire 1 P lc [1] $end
$var wire 1 Q lc [0] $end
$var wire 1 R cc [7] $end
$var wire 1 S cc [6] $end
$var wire 1 T cc [5] $end
$var wire 1 U cc [4] $end
$var wire 1 V cc [3] $end
$var wire 1 W cc [2] $end
$var wire 1 X cc [1] $end
$var wire 1 Y cc [0] $end
$var wire 1 Z rc [7] $end
$var wire 1 [ rc [6] $end
$var wire 1 \ rc [5] $end
$var wire 1 ] rc [4] $end
$var wire 1 ^ rc [3] $end
$var wire 1 _ rc [2] $end
$var wire 1 ` rc [1] $end
$var wire 1 a rc [0] $end
$var wire 1 b lb [7] $end
$var wire 1 c lb [6] $end
$var wire 1 d lb [5] $end
$var wire 1 e lb [4] $end
$var wire 1 f lb [3] $end
$var wire 1 g lb [2] $end
$var wire 1 h lb [1] $end
$var wire 1 i lb [0] $end
$var wire 1 j cb [7] $end
$var wire 1 k cb [6] $end
$var wire 1 l cb [5] $end
$var wire 1 m cb [4] $end
$var wire 1 n cb [3] $end
$var wire 1 o cb [2] $end
$var wire 1 p cb [1] $end
$var wire 1 q cb [0] $end
$var wire 1 r rb [7] $end
$var wire 1 s rb [6] $end
$var wire 1 t rb [5] $end
$var wire 1 u rb [4] $end
$var wire 1 v rb [3] $end
$var wire 1 w rb [2] $end
$var wire 1 x rb [1] $end
$var wire 1 y rb [0] $end
$var wire 1 * blurred [7] $end
$var wire 1 + blurred [6] $end
$var wire 1 , blurred [5] $end
$var wire 1 - blurred [4] $end
$var wire 1 . blurred [3] $end
$var wire 1 / blurred [2] $end
$var wire 1 0 blurred [1] $end
$var wire 1 1 blurred [0] $end
$var reg 10 z cc4 [9:0] $end
$var reg 9 { lc2 [8:0] $end
$var reg 9 | cu2 [8:0] $end
$var reg 9 } rc2 [8:0] $end
$var reg 9 ~ cb2 [8:0] $end
$var reg 12 !! sum [11:0] $end
$upscope $end
$upscope $end
$enddefinitions $end
#0
$dumpvars
b10111000 !
b10110110 "
b1110010 #
b100110 $
b11000110 %
b101110 &
b1100110 '
b1000110 (
b1100111 )
b1100011000 z
b1001100 {
b101101100 |
b1011100 }
b10001100 ~
b11110101111 !!
01
10
0/
1.
1-
1,
1+
0*
1y
1x
1w
0v
0u
1t
1s
0r
0q
1p
1o
0n
0m
0l
1k
0j
0i
1h
1g
0f
0e
1d
1c
0b
0a
1`
1_
1^
0]
1\
0[
0Z
0Y
1X
1W
0V
0U
0T
1S
1R
0Q
1P
1O
0N
0M
1L
0K
0J
0I
1H
0G
0F
1E
1D
1C
0B
0A
1@
1?
0>
1=
1<
0;
1:
09
08
07
16
15
14
03
12
$end
#100
b111010 !
b1101010 $
b10110100 '
b1101111 "
b1010110 %
b110101 (
b11010100 #
b10101110 &
b1111101 )
0x
1v
1u
1Z
0H
1G
0D
1B
1q
0p
1m
1l
0k
1U
0R
1A
1>
0=
1;
0:
0h
1e
0c
1b
0O
1N
1K
18
02
b1010110 z
b1101010 {
b1101111 |
b10101110 }
b110101 ~
b101011000 z
b11010100 {
b11011110 |
b101011100 }
b1101010 ~
b11100001111 !!
00
0.
#200
b11011011 !
b101 $
b11100011 '
b100000 "
b11100101 %
b101 (
b100101 #
b11101001 &
b1011101 )
0t
1a
0`
0_
1[
1I
0E
1D
0C
0B
0m
0l
1Y
0X
0U
1T
1R
0A
0@
0?
0>
0;
1i
1h
0g
0e
1c
1Q
0P
1O
0N
0L
0K
19
04
13
12
b11100101 z
b101 {
b100000 |
b11101001 }
b101 ~
b1110010100 z
b1010 {
b1000000 |
b111010010 }
b1010 ~
b11111111010 !!
11
10
1/
1.
#300
b10001010 !
b1011000 $
b10001011 '
b1010110 "
b11001001 %
b10111001 (
b1000000 #
b10000000 &
b1110 )
0y
1x
0u
0s
0a
0^
0\
0[
0I
0G
0D
1C
0o
1n
1m
1l
1j
0W
1V
0T
1@
1?
1=
0<
1;
1f
0d
0c
0Q
0O
1N
1M
1K
09
05
03
b11001001 z
b1011000 {
b1010110 |
b10000000 }
b10111001 ~
b1100100100 z
b10110000 {
b10101100 |
b100000000 }
b101110010 ~
b100001010101 !!
00
0.
0-
0,
0+
1*
#400
b11010100 !
b10001110 $
b11000000 '
b10010111 "
b100101 %
b11000111 (
b1011000 #
b1010001 &
b110010 )
0w
0v
1u
1t
1a
1]
1[
0Z
1F
1E
1p
1o
0n
0m
0l
1k
1W
0V
1T
0S
0R
1A
0;
1:
0i
0h
0f
1c
1P
1O
0M
0K
1J
08
17
06
15
13
b100101 z
b10001110 {
b10010111 |
b1010001 }
b11000111 ~
b10010100 z
b100011100 {
b100101110 |
b10100010 }
b110001110 ~
b11100101100 !!
01
10
0/
1-
1,
1+
0*
#500
b100011 !
b1010100 $
b10110011 '
b1011010 "
b11100110 %
b11110110 (
b1100101 #
b11101010 &
b1111 )
1y
1w
1v
0u
0t
0a
1`
1^
0]
1\
1Z
1I
1G
0F
0E
1D
0q
1m
1l
0Y
1X
1S
1R
0A
0?
1>
1;
0:
1i
1h
1e
1d
0c
0P
0N
1M
1K
0J
19
18
07
05
14
03
02
b11100110 z
b1010100 {
b1011010 |
b11101010 }
b11110110 ~
b1110011000 z
b10101000 {
b10110100 |
b111010100 }
b111101100 ~
b100111111110 !!
11
1/
1.
0,
0+
1*
#600
b11101111 !
b1000100 $
b11001001 '
b11001011 "
b1000111 %
b11000111 (
b11110010 #
b11100001 &
b10000101 )
0x
0v
1r
1a
0`
0^
0I
1H
0G
1E
1B
1q
0m
0l
1Y
0T
0R
1A
0=
1:
0h
1f
0e
0d
1c
0M
17
16
13
12
b1000111 z
b1000100 {
b11001011 |
b11100001 }
b11000111 ~
b100011100 z
b10001000 {
b110010110 |
b111000010 }
b110001110 ~
b100110111001 !!
0/
#700
b110000 !
b1110110 $
b11101 '
b11010010 "
b10110 %
b11011011 (
b1000000 #
b10110101 &
b10010001 )
0w
1u
1_
1]
0[
0H
0E
0D
0B
0o
1n
1m
0Y
1U
0S
0A
0>
1=
1g
1e
0c
0b
1P
1M
1L
09
08
07
06
15
03
02
b10110 z
b1110110 {
b11010010 |
b10110101 }
b11011011 ~
b1011000 z
b11101100 {
b110100100 |
b101101010 }
b110110110 ~
b11100100110 !!
01
0.
1,
1+
0*
#800
b1110011 !
b10100000 $
b1010111 '
b11101 "
b11010100 %
b11011101 (
b10011010 #
b10000100 &
b10110111 )
1x
1w
1t
0a
0]
0\
1H
1F
1E
0C
1B
0p
1o
0X
1S
1R
1A
0@
1?
1>
0;
0:
1h
0f
1c
0P
0O
0M
0K
1J
19
18
13
b11010100 z
b10100000 {
b11101 |
b10000100 }
b11011101 ~
b1101010000 z
b101000000 {
b111010 |
b100001000 }
b110111010 ~
b100110100111 !!
1.
0,
0+
1*
#900
b10001001 !
b1010 $
b11010101 '
b11111110 "
b1001100 %
b11111110 (
b11000011 #
b10001000 &
b10111100 )
0y
0x
1v
0_
1^
1I
0F
0E
1C
0q
1p
1l
1V
0U
0R
0A
1@
1<
1;
1:
0h
1b
1P
1N
0L
0J
08
16
05
04
03
12
b1001100 z
b1010 {
b11111110 |
b10001000 }
b11111110 ~
b100110000 z
b10100 {
b111111100 |
b100010000 }
b111111100 ~
b100100101001 !!
0.
#1000
b10011011 !
b11110011 $
b101111 '
b10110111 "
b1011 %
b11100111 (
b0 #
b1001 &
b1101010 )
1x
0w
0u
1s
0r
1a
0Z
0I
0H
0C
0B
1q
0n
0m
1Y
1X
0W
0S
1A
0>
0;
1h
1f
0e
1d
0c
0b
1Q
0N
1M
1L
1K
1J
18
15
b1011 z
b11110011 {
b10110111 |
b1001 }
b11100111 ~
b101100 z
b111100110 {
b101101110 |
b10010 }
b111001110 ~
b11010010100 !!
11
00
1.
0-
1,
1+
0*
#1100
b11000001 !
b100 $
b1100000 '
b10101111 "
b1101111 %
b1000101 (
b11001101 #
b1101100 &
b11010000 )
0x
0v
1u
0t
1r
0a
1_
1\
1[
1I
1G
1F
1C
1B
0p
0l
0j
1W
1T
1S
1>
0=
0i
0h
0g
0f
1c
0Q
0P
1O
0M
0L
0K
0J
08
06
05
13
b1101111 z
b100 {
b10101111 |
b1101100 }
b1000101 ~
b110111100 z
b1000 {
b101011110 |
b11011000 }
b10001010 ~
b11101000010 !!
01
1/
0.
1-
#1200
b10101001 !
b11111100 $
b11100101 '
b10100111 "
b111011 %
b10111110 (
b10100001 #
b10000101 &
b10001110 )
1x
1w
1v
0u
0s
1a
0^
0\
0[
1Z
0G
0F
1D
0C
0q
1p
1n
1m
1l
0k
1j
0W
1U
0S
0>
1i
1g
1b
1N
1M
1L
1K
1J
16
14
03
b111011 z
b11111100 {
b10100111 |
b10000101 }
b10111110 ~
b11101100 z
b111111000 {
b101001110 |
b100001010 }
b101111100 ~
b100101110101 !!
11
10
0,
0+
1*
#1300
b10100000 !
b10101 $
b0 '
b11000100 "
b10001011 %
b10101000 (
b10111101 #
b1101100 &
b1111101 )
1y
0x
1u
1t
1s
0r
0a
1^
1\
1[
0Z
1G
1F
1E
0p
0o
0m
0U
0T
1R
0A
0@
0<
1;
0i
0g
0d
0c
0b
1Q
0N
0L
0K
0J
09
06
b10001011 z
b10101 {
b11000100 |
b1101100 }
b10101000 ~
b1000101100 z
b101010 {
b110001000 |
b11011000 }
b101010000 ~
b11111100000 !!
01
1.
1,
1+
0*
#1400
b10101011 !
b10101010 $
b1100001 '
b10110010 "
b1010110 %
b1000110 (
b11010100 #
b11100001 &
b11010100 )
0y
0v
0t
1r
1a
0_
0^
1Z
0I
0F
0D
1C
1p
1o
0n
0l
1k
0j
0Y
1W
0V
1U
1S
0R
1@
0?
1=
1<
0;
1i
1d
1c
0Q
1P
0O
1N
0M
1L
1J
19
18
16
b1010110 z
b10101010 {
b10110010 |
b11100001 }
b1000110 ~
b101011000 z
b101010100 {
b101100100 |
b111000010 }
b10001100 ~
b100100010010 !!
11
00
0/
0.
0,
0+
1*
#1500
b100001 !
b1100000 $
b1101001 '
b110 "
b11110100 %
b1111110 (
b11001010 #
b101000 &
b11 )
1y
1x
0w
0u
0s
0r
0a
1^
0[
0Z
1H
0G
1F
0E
1n
1m
1l
0X
1T
1R
1?
0=
0<
0:
1f
0P
0N
1K
0J
08
06
02
b11110100 z
b1100000 {
b110 |
b101000 }
b1111110 ~
b1111010000 z
b11000000 {
b1100 |
b1010000 }
b11111100 ~
b11100111111 !!
10
1,
1+
0*
#1600
b10101111 !
b11101100 $
b1111110 '
b1000110 "
b1001000 %
b11000101 (
b11111110 #
b10100100 &
b1110101 )
0x
1w
1u
1t
1s
1_
0^
1Z
1G
1E
1D
1q
0p
0n
0m
0l
1j
0W
1V
0U
0T
0R
1;
0i
1h
1g
1e
1O
1N
1J
18
17
16
12
b1001000 z
b11101100 {
b1000110 |
b10100100 }
b11000101 ~
b100100000 z
b111011000 {
b10001100 |
b101001000 }
b110001010 ~
b100011110110 !!
1/
1.
0-
0,
0+
1*
#1700
b1101 !
b1110110 $
b1111101 '
b11111 "
b11111001 %
b1111001 (
b100001 #
b1101101 &
b11011101 )
1v
0t
1r
1a
1^
1[
0Z
1I
0H
0G
0F
0E
0C
0B
0o
1n
1m
1l
0j
1Y
1U
1T
1R
1A
1>
1=
0;
1i
0h
1P
0N
1M
0J
08
04
02
b11111001 z
b1110110 {
b11111 |
b1101101 }
b1111001 ~
b1111100100 z
b11101100 {
b111110 |
b11011010 }
b11110010 ~
b100001100010 !!
01
0.
#1800
b11001111 !
b11110001 $
b1100101 '
b10011010 "
b1110000 %
b10101000 (
b1110110 #
b11101110 &
b10110100 )
0y
0v
1t
0s
0a
1`
1Z
0I
1H
1G
1E
1C
0q
0m
0k
1j
0Y
0V
0R
0A
0?
1:
0f
0e
1Q
0P
0O
1J
18
13
12
b1110000 z
b11110001 {
b10011010 |
b11101110 }
b10101000 ~
b111000000 z
b111100010 {
b100110100 |
b111011100 }
b101010000 ~
b101001100000 !!
1,
#1900
b11000 !
b1010001 $
b1111100 '
b1001101 "
b11000001 %
b10110111 (
b1000110 #
b11110000 &
b100111 )
1y
1x
0u
0r
0`
0_
0^
1]
0E
0D
1q
1p
1o
0n
1m
1Y
0U
0T
1R
1A
0@
1?
0=
1;
0:
0i
1f
1e
0L
0J
09
08
07
15
03
02
b11000001 z
b1010001 {
b1001101 |
b11110000 }
b10110111 ~
b1100000100 z
b10100010 {
b10011010 |
b111100000 }
b101101110 ~
b100010001111 !!
00
0/
1.
0,
#2000
b1110011 !
b111100 $
b10010110 '
b11001000 "
b1000010 %
b100110 (
b111001 #
b1110011 &
b10101111 )
1v
1r
1a
1`
0Z
1I
0H
0G
1F
1E
1D
0C
0q
0m
0j
0Y
1X
0R
0A
0?
1:
1h
0f
0d
0c
1b
0Q
1O
1N
1L
0K
19
18
06
14
13
b1000010 z
b111100 {
b11001000 |
b1110011 }
b100110 ~
b100001000 z
b1111000 {
b110010000 |
b11100110 }
b1001100 ~
b11000110011 !!
11
10
0.
1,
1+
0*
#2100
b10110100 !
b1100111 $
b11001000 '
b11101011 "
b1010010 %
b10001010 (
b1001110 #
b101100 &
b11011111 )
1u
0t
1s
0a
0`
1_
1^
0]
0[
0I
1H
1G
0E
0D
1C
0o
1n
0l
1j
1U
1A
1@
1<
0h
0g
1f
0e
1c
1Q
1P
0N
0M
1K
09
08
17
03
12
b1010010 z
b1100111 {
b11101011 |
b101100 }
b10001010 ~
b101001000 z
b11001110 {
b111010110 |
b1011000 }
b100010100 ~
b100000000001 !!
01
00
0,
0+
1*
#2200
b11000111 !
b10010001 $
b11110101 '
b11101010 "
b1101111 %
b10010101 (
b100100 #
b10110 &
b11101000 )
0y
0x
0w
0u
1t
1`
0^
1]
0\
0H
0F
1D
0C
1q
0p
1o
0n
1m
1Y
1W
1V
0U
1T
0A
1i
1g
0f
1e
1d
0P
0O
1M
0L
0K
1J
19
18
05
04
13
b1101111 z
b10010001 {
b11101010 |
b10110 }
b10010101 ~
b110111100 z
b100100010 {
b111010100 |
b101100 }
b100101010 ~
b100011010000 !!
11
1/
1.
#2300
b1010100 !
b1010100 $
b1010001 '
b1011100 "
b11000011 %
b10101011 (
b10001100 #
b11110 &
b10101110 )
1x
1w
0s
1^
1F
0D
1B
1p
0o
1n
0m
1l
0W
0V
0T
1R
0@
1?
1=
0<
0:
0g
0d
0b
0Q
1O
1K
0J
09
08
15
02
b11000011 z
b1010100 {
b1011100 |
b11110 }
b10101011 ~
b1100001100 z
b10101000 {
b10111000 |
b111100 }
b101010110 ~
b11111011101 !!
1-
1,
1+
0*
#2400
b11110101 !
b11011110 $
b1 '
b11000000 "
b10000000 %
b11001000 (
b11101101 #
b10101010 &
b100101 )
1y
0x
0v
0r
0_
0]
1\
1Z
1I
1D
1C
0q
0p
0l
1k
0Y
0X
0S
0?
0>
0=
1:
0e
0c
1P
1N
1J
19
14
12
b10000000 z
b11011110 {
b11000000 |
b10101010 }
b11001000 ~
b1000000000 z
b110111100 {
b110000000 |
b101010100 }
b110010000 ~
b101000101000 !!
01
10
0/
0.
0-
0+
1*
#2500
b1011001 !
b1110100 $
b10110110 '
b11110 "
b1100010 %
b10101000 (
b1001111 #
b10101111 &
b1010011 )
1x
0w
1u
0t
1s
1a
1_
1H
0D
0B
1l
0k
1X
1T
1S
0R
1@
1?
1>
1=
0;
0:
0i
1h
1g
1e
1d
1b
0P
0N
1L
0J
07
16
04
02
b1100010 z
b1110100 {
b11110 |
b10101111 }
b10101000 ~
b110001000 z
b11101000 {
b111100 |
b101011110 }
b101010000 ~
b11100001011 !!
00
1-
1+
0*
#2600
b10110101 !
b110101 $
b11101 '
b1001000 "
b101100 %
b11011011 (
b10010000 #
b10110 &
b10010110 )
0y
1w
0s
1r
0a
0^
1]
0\
0Z
0I
0H
0G
0F
1E
0C
1B
1q
1p
1m
0l
1k
0X
1W
1V
0S
0@
0?
0=
1;
1i
0h
1f
0d
0b
1Q
0K
17
06
14
03
12
b101100 z
b110101 {
b1001000 |
b10110 }
b11011011 ~
b10110000 z
b1101010 {
b10010000 |
b101100 }
b110110110 ~
b10110000100 !!
1.
0,
#2700
b10100100 !
b11111110 $
b11100000 '
b10000110 "
b11100000 %
b1011011 (
b10001 #
b11001110 &
b11010000 )
0x
0w
1s
1^
0]
1[
1Z
1I
0B
0j
0W
0V
1S
1R
1@
1?
0>
0;
1:
0i
0g
0f
0e
1d
1c
1b
0Q
1P
1N
1K
1J
09
05
b11100000 z
b11111110 {
b10000110 |
b11001110 }
b1011011 ~
b1110000000 z
b111111100 {
b100001100 |
b110011100 }
b10110110 ~
b101100111111 !!
11
10
0.
1,
0+
1*
#2800
b10011001 !
b10000 $
b10000110 '
b10100110 "
b1000001 %
b10011 (
b10010 #
b10100111 &
b10001011 )
1y
1x
1v
0u
0s
1a
0^
1\
0[
0I
1H
0n
0k
1Y
0T
0R
1<
1h
1g
0d
0c
0P
0O
0N
0L
0K
0J
19
07
16
15
04
b1000001 z
b10000 {
b10100110 |
b10100111 }
b10011 ~
b100000100 z
b100000 {
b101001100 |
b101001110 }
b100110 ~
b10110100000 !!
01
1.
0,
1+
0*
#2900
b10011011 !
b1011 $
b1010 '
b1111 "
b11110111 %
b10101001 (
b11001111 #
b11101010 &
b11001111 )
1w
1s
0a
0_
1^
1[
1I
1G
1F
0E
1C
1B
0p
1n
0m
1l
1j
1X
1W
1U
1T
1R
1A
1>
0<
0:
0g
1f
0b
1Q
1P
1N
0M
18
b11110111 z
b1011 {
b1111 |
b11101010 }
b10101001 ~
b1111011100 z
b10110 {
b11110 |
b111010100 }
b101010010 ~
b100101111001 !!
11
1/
0.
0+
1*
#3000
b1000010 !
b1101001 $
b111100 '
b110100 "
b11111100 %
b1010001 (
b10011100 #
b10110010 &
b11010111 )
0v
1u
0^
1]
0[
0I
0H
1E
0C
0n
1m
0l
1k
0j
0Y
0X
1V
0A
0@
0>
1=
1<
0h
1g
1e
1d
0P
1L
1K
09
06
05
13
02
b11111100 z
b1101001 {
b110100 |
b10110010 }
b1010001 ~
b1111110000 z
b11010010 {
b1101000 |
b101100100 }
b10100010 ~
b100100100001 !!
01
0/
#3100
b100111 !
b10100001 $
b1010011 '
b11000001 "
b11111011 %
b10011 (
b10011101 #
b11010101 &
b1001001 )
0x
0w
1v
0u
0r
1a
0`
1_
0\
1[
1I
1p
0k
1Y
1X
0W
1A
0?
0=
0<
1;
1:
1i
1h
0g
0f
0d
1c
0N
0K
1J
19
17
14
03
b11111011 z
b10100001 {
b11000001 |
b11010101 }
b10011 ~
b1111101100 z
b101000010 {
b110000010 |
b110101010 }
b100110 ~
b100111100000 !!
1/
1.
#3200
b1110010 !
b1 $
b1001111 '
b10101110 "
b11010100 %
b10001011 (
b10101 #
b1 &
b10110101 )
1w
0v
1u
1t
0s
1r
0_
0]
0[
0Z
0F
0B
1n
0m
1j
0Y
0X
1W
0V
0T
0A
1@
1?
1>
1<
0;
1g
1f
0e
0L
0J
09
07
15
13
b11010100 z
b1 {
b10101110 |
b1 }
b10001011 ~
b1101010000 z
b10 {
b101011100 |
b10 }
b100010110 ~
b11101010001 !!
11
00
0.
1,
1+
0*
#3300
b11100000 !
b1111 $
b1011011 '
b100000 "
b1000000 %
b10001100 (
b11011001 #
b11110011 &
b10010111 )
1x
0t
1`
1]
1\
1[
1Z
0G
1F
1C
1B
0q
0p
1o
0W
0U
0R
0@
0?
0>
0:
0g
1e
1P
1O
1N
08
05
12
b1000000 z
b1111 {
b100000 |
b11110011 }
b10001100 ~
b100000000 z
b11110 {
b1000000 |
b111100110 }
b100011000 ~
b11100000111 !!
01
0/
#3400
b10001101 !
b10000110 $
b10011100 '
b1010100 "
b1001101 %
b101101 (
b101100 #
b11111000 &
b1010000 )
0y
0x
0w
1s
0r
0a
0`
1^
0I
1G
0E
1D
0C
0B
1q
1l
0j
1Y
1W
1V
1?
1=
0<
1;
0i
0h
1g
0c
1b
0Q
0N
1J
19
17
16
04
03
b1001101 z
b10000110 {
b1010100 |
b11111000 }
b101101 ~
b100110100 z
b100001100 {
b10101000 |
b111110000 }
b1011010 ~
b11011010111 !!
11
1/
1.
0-
#3500
b10001011 !
b11110000 $
b10111000 '
b10100001 "
b10111100 %
b1010 (
b10100010 #
b11001000 &
b110011 )
1y
1x
1t
0s
0]
0\
1H
0G
0F
1B
0q
1p
0o
0l
0Y
1U
1T
0S
1R
1A
0?
0=
1<
0;
1:
0g
1d
0P
0O
1M
1L
1K
18
07
b10111100 z
b11110000 {
b10100001 |
b11001000 }
b1010 ~
b1011110000 z
b111100000 {
b101000010 |
b110010000 }
b10100 ~
b100111001110 !!
01
1-
0,
0+
1*
#3600
b10000 !
b11000110 $
b110110 '
b1010000 "
b10010010 %
b110011 (
b10111 #
b10010110 &
b1110101 )
0x
1w
1s
1`
1_
0^
1]
0[
1I
1G
1E
0D
0B
1q
0n
1m
1l
1X
0W
0V
0T
0A
1=
0<
1;
0:
1h
1g
0f
0b
1P
1O
0M
0L
09
08
06
15
02
b10010010 z
b11000110 {
b1010000 |
b10010110 }
b110011 ~
b1001001000 z
b110001100 {
b10100000 |
b100101100 }
b1100110 ~
b11011011000 !!
11
0-
1,
1+
0*
#3700
b10011010 !
b101001 $
b1100100 '
b11011100 "
b11000 %
b111000 (
b1101011 #
b11000100 &
b1101001 )
0w
1v
0u
0`
0]
1[
0G
1F
0E
1D
1C
0q
0p
1n
0X
1V
0R
1?
1>
1:
0h
0e
1c
1Q
0P
0O
1N
1L
0K
0J
18
16
12
b11000 z
b101001 {
b11011100 |
b11000100 }
b111000 ~
b1100000 z
b1010010 {
b110111000 |
b110001000 }
b1110000 ~
b11000110100 !!
10
0/
0.
#3800
b1001001 !
b10001011 $
b11100010 '
b11100001 "
b1100010 %
b11101000 (
b11010100 #
b1101111 &
b10111000 )
0y
1u
0s
1r
1a
1`
1^
1\
0Z
0I
0H
1G
0F
1E
0D
1B
0m
1k
1j
1X
0V
0U
1T
1S
1A
0?
0>
0=
1<
1h
0g
1b
1P
0L
1J
19
08
05
13
02
b1100010 z
b10001011 {
b11100001 |
b1101111 }
b11101000 ~
b110001000 z
b100010110 {
b111000010 |
b11011110 }
b111010000 ~
b100111000101 !!
01
00
1/
1.
1-
0,
0+
1*
#3900
b11011 !
b11010011 $
b11011 '
b1000100 "
b111000 %
b10010010 (
b100111 #
b11001010 &
b10110111 )
1y
1x
1w
0v
0a
0_
0\
1Z
1I
1H
0E
1D
0C
0B
1p
0n
1m
0l
0k
0X
1V
1U
0S
0A
1?
0<
0:
1i
1f
1e
0d
0c
0b
0N
1M
1K
18
15
03
b111000 z
b11010011 {
b1000100 |
b11001010 }
b10010010 ~
b11100000 z
b110100110 {
b10001000 |
b110010100 }
b100100100 ~
b11011011010 !!
11
0-
1,
1+
0*
#4000
b10011100 !
b10101100 $
b11100101 '
b111010 "
b10011100 %
b11010001 (
b1100101 #
b11011 &
b1000111 )
0u
0t
1s
0r
1a
1]
0[
0Z
0H
1C
1q
0p
1k
1W
0T
1R
1@
0?
1>
1=
1<
0;
0h
1g
0f
0e
1d
1c
1b
0Q
0P
1O
1N
0M
1L
0K
09
08
17
12
b10011100 z
b10101100 {
b111010 |
b11011 }
b11010001 ~
b1001110000 z
b101011000 {
b1110100 |
b110110 }
b110100010 ~
b100001000001 !!
01
0.
0,
0+
1*
#4100
b10110 !
b1101011 $
b111110 '
b10111000 "
b11 %
b10100101 (
b10111000 #
b1111100 &
b11100 )
0y
0x
1v
1u
0s
0a
0`
1_
1\
1[
0I
0G
1F
1E
0C
1B
1o
0m
1l
0k
1Y
1X
0W
0V
0U
0R
0@
1:
0i
1h
1f
1e
0c
0b
1Q
1P
0O
1K
0J
18
06
02
b11 z
b1101011 {
b10111000 |
b1111100 }
b10100101 ~
b1100 z
b11010110 {
b101110000 |
b11111000 }
b101001010 ~
b10110111100 !!
11
10
0/
1.
1-
1+
0*
#4200
b1101011 !
b11101010 $
b100000 '
b11000101 "
b11000001 %
b1110001 (
b10010 #
b1100101 &
b10011110 )
1x
1r
1a
0^
0]
1H
0F
0D
0B
0o
1m
1k
0j
0X
1S
1R
1A
1?
0>
0=
0<
1;
0h
0g
0f
0e
0Q
1J
19
07
16
05
14
13
b11000001 z
b11101010 {
b11000101 |
b1100101 }
b1110001 ~
b1100000100 z
b111010100 {
b110001010 |
b11001010 }
b11100010 ~
b100101001001 !!
01
00
1/
0.
0+
1*
#4300
b1001011 !
b11111101 $
b11100001 '
b10001010 "
b1110001 %
b1110011 (
b11011101 #
b10111 &
b11001101 )
1y
0x
0u
1s
1`
1]
0\
0[
1I
0H
1G
1F
1C
1B
1p
1U
1T
0R
0A
1@
0?
1>
0;
1i
1c
1b
1Q
0P
1O
1M
04
b1110001 z
b11111101 {
b10001010 |
b10111 }
b1110011 ~
b111000100 z
b111111010 {
b100010100 |
b101110 }
b11100110 ~
b100010111100 !!
11
10
0/
1.
0-
#4400
b1011 !
b11010001 $
b1101100 '
b11111010 "
b10111 %
b11011011 (
b100 #
b11110100 &
b10000000 )
0y
0w
0v
0s
0a
0`
1\
1[
1Z
0I
0F
0E
0C
0B
1n
0l
1j
1X
1W
0T
0S
1=
1<
1;
0i
1g
1f
0b
0O
0N
0L
03
b10111 z
b11010001 {
b11111010 |
b11110100 }
b11011011 ~
b1011100 z
b110100010 {
b111110100 |
b111101000 }
b110110110 ~
b100010001011 !!
01
00
#4500
b11111 !
b11000 $
b1100010 '
b11100000 "
b1000111 %
b1011110 (
b110001 #
b110011 &
b1 )
1y
0r
1a
1`
0_
0[
0Z
1I
0G
1E
1D
0q
1o
0j
0U
1S
0@
0>
0=
1h
0g
0f
0Q
1N
0K
0J
17
15
b1000111 z
b11000 {
b11100000 |
b110011 }
b1011110 ~
b100011100 z
b110000 {
b111000000 |
b1100110 }
b10111100 ~
b10011100001 !!
10
1/
1+
0*
#4600
b110011 !
b11011 $
b1111111 '
b11110011 "
b10000110 %
b1111000 (
b10001 #
b11 &
b10110110 )
0y
1x
1w
1u
1t
1r
0]
0\
0D
0p
0o
1l
0Y
0S
1R
1A
1@
1=
1i
1g
1f
1e
1Q
1P
07
06
14
b10000110 z
b11011 {
b11110011 |
b11 }
b1111000 ~
b1000011000 z
b110110 {
b111100110 |
b110 }
b11110000 ~
b11010100011 !!
0/
1,
